{"meta": {"mode": "PAPER / DEMO", "generated": "2026-07-20 00:25", "generated_ms": 1784507111075, "inception": "2026-07-01 19:33", "days": 22, "pairs": ["CRCLBUSDT", "MSTRBUSDT", "MUBUSDT", "NVDABUSDT", "QQQBUSDT", "SNDKBUSDT", "SPCXBUSDT", "TSLABUSDT"], "capital": 100.0, "pos_size": 34.06, "pos_fraction": 0.34, "sizing": "compounding", "max_concurrent": 3, "fee_round_trip_pct": 0.15, "strategy": {"name": "Active \u00b7 24/7 dip", "desc": "around-the-clock oversold-dip buyer on the most liquid bStocks", "min_edge": 60, "rsi_1h_max": 45.0, "tp": 0.022, "sl": 0.009, "market_hours": false}, "data_source": "Binance public /api/v3 klines (no keys)", "benchmark_note": "SPY/QQQ aren't on Binance spot; benchmark is an equal-weight buy-and-hold of the traded basket."}, "account": {"equity": 100.63, "cash": 66.13, "realized_pnl": 0.19, "unrealized_pnl": 0.44, "total_return_pct": 0.63, "open_positions": 1}, "performance": {"closed_trades": 67, "wins": 24, "losses": 43, "win_rate": 35.8, "best": 0.72, "worst": -0.37, "signals_skipped_no_capital": 12, "avg_hold_min": 388.0}, "benchmark": {"hold_return_pct": -9.66, "vs_hold_pct": 10.29, "beats_hold": true, "qqq_symbol": "QQQB", "qqq_return_pct": -3.56, "qqq_days": 18.2, "vs_qqq_pct": 4.19, "beats_qqq": true}, "per_pair": {"CRCLBUSDT": {"trades": 11, "wins": 5, "pnl": 1.42}, "MSTRBUSDT": {"trades": 8, "wins": 1, "pnl": -1.78}, "MUBUSDT": {"trades": 12, "wins": 6, "pnl": 1.62}, "NVDABUSDT": {"trades": 11, "wins": 4, "pnl": -0.27}, "QQQBUSDT": {"trades": 6, "wins": 3, "pnl": 0.72}, "SNDKBUSDT": {"trades": 6, "wins": 2, "pnl": -0.02}, "SPCXBUSDT": {"trades": 9, "wins": 3, "pnl": -0.08}, "TSLABUSDT": {"trades": 4, "wins": 0, "pnl": -1.42}}, "open_trades": [{"symbol": "MSTRBUSDT", "side": "LONG", "entry_ts": 1784483100000, "planned_exit_ts": 1784569500000, "entry_px": 94.82, "exit_px": 96.11, "size": 34.06, "pnl_usd": 0.41, "net_pct": 1.21, "outcome": "TIMEOUT", "edge": 63, "hold_min": 1440, "rsi_1h": 36.57, "rsi_15m": 28.51, "mark_px": 96.11, "unrealized_usd": 0.44}], "closed_trades": [{"symbol": "MUBUSDT", "side": "LONG", "entry_ts": 1784393100000, "planned_exit_ts": 1784479500000, "entry_px": 838.0, "exit_px": 847.79, "size": 33.95, "pnl_usd": 0.35, "net_pct": 1.018, "outcome": "TIMEOUT", "edge": 63, "hold_min": 1440, "rsi_1h": 33.34, "rsi_15m": 27.56, "exit_ts": 1784479500000}, {"symbol": "TSLABUSDT", "side": "LONG", "entry_ts": 1784209500000, "planned_exit_ts": 1784276220000, "entry_px": 387.26, "exit_px": 383.7747, "size": 32.14, "pnl_usd": -0.34, "net_pct": -1.05, "outcome": "LOSS", "edge": 83, "hold_min": 1112, "rsi_1h": 32.75, "rsi_15m": 19.8, "exit_ts": 1784276220000}, {"symbol": "CRCLBUSDT", "side": "LONG", "entry_ts": 1784209500000, "planned_exit_ts": 1784211060000, "entry_px": 61.89, "exit_px": 63.2516, "size": 33.94, "pnl_usd": 0.7, "net_pct": 2.05, "outcome": "WIN", "edge": 63, "hold_min": 26, "rsi_1h": 30.67, "rsi_15m": 25.32, "exit_ts": 1784211060000}, {"symbol": "QQQBUSDT", "side": "LONG", "entry_ts": 1784126700000, "planned_exit_ts": 1784210100000, "entry_px": 715.21, "exit_px": 708.7731, "size": 33.75, "pnl_usd": -0.35, "net_pct": -1.05, "outcome": "LOSS", "edge": 63, "hold_min": 1390, "rsi_1h": 32.35, "rsi_15m": 25.37, "exit_ts": 1784210100000}, {"symbol": "NVDABUSDT", "side": "LONG", "entry_ts": 1784189700000, "planned_exit_ts": 1784209500000, "entry_px": 209.35, "exit_px": 207.4658, "size": 33.96, "pnl_usd": -0.36, "net_pct": -1.05, "outcome": "LOSS", "edge": 63, "hold_min": 330, "rsi_1h": 42.55, "rsi_15m": 25.6, "exit_ts": 1784209500000}, {"symbol": "SPCXBUSDT", "side": "LONG", "entry_ts": 1784205900000, "planned_exit_ts": 1784208720000, "entry_px": 134.14, "exit_px": 137.0911, "size": 31.83, "pnl_usd": 0.65, "net_pct": 2.05, "outcome": "WIN", "edge": 73, "hold_min": 47, "rsi_1h": 34.63, "rsi_15m": 22.87, "exit_ts": 1784208720000}, {"symbol": "MSTRBUSDT", "side": "LONG", "entry_ts": 1784193300000, "planned_exit_ts": 1784205840000, "entry_px": 95.86, "exit_px": 94.9973, "size": 32.17, "pnl_usd": -0.34, "net_pct": -1.05, "outcome": "LOSS", "edge": 63, "hold_min": 209, "rsi_1h": 32.79, "rsi_15m": 34.16, "exit_ts": 1784205840000}, {"symbol": "MSTRBUSDT", "side": "LONG", "entry_ts": 1784187900000, "planned_exit_ts": 1784189520000, "entry_px": 96.44, "exit_px": 95.572, "size": 34.08, "pnl_usd": -0.36, "net_pct": -1.05, "outcome": "LOSS", "edge": 63, "hold_min": 27, "rsi_1h": 41.07, "rsi_15m": 32.17, "exit_ts": 1784189520000}, {"symbol": "SPCXBUSDT", "side": "LONG", "entry_ts": 1784132100000, "planned_exit_ts": 1784137740000, "entry_px": 133.0, "exit_px": 135.926, "size": 33.63, "pnl_usd": 0.69, "net_pct": 2.05, "outcome": "WIN", "edge": 73, "hold_min": 94, "rsi_1h": 30.83, "rsi_15m": 20.43, "exit_ts": 1784137740000}, {"symbol": "MUBUSDT", "side": "LONG", "entry_ts": 1784134800000, "planned_exit_ts": 1784137620000, "entry_px": 891.48, "exit_px": 911.0926, "size": 31.52, "pnl_usd": 0.65, "net_pct": 2.05, "outcome": "WIN", "edge": 65, "hold_min": 47, "rsi_1h": 30.0, "rsi_15m": 22.28, "exit_ts": 1784137620000}, {"symbol": "NVDABUSDT", "side": "LONG", "entry_ts": 1784128500000, "planned_exit_ts": 1784131500000, "entry_px": 209.51, "exit_px": 207.6244, "size": 33.75, "pnl_usd": -0.35, "net_pct": -1.05, "outcome": "LOSS", "edge": 63, "hold_min": 50, "rsi_1h": 30.19, "rsi_15m": 28.36, "exit_ts": 1784131500000}, {"symbol": "SPCXBUSDT", "side": "LONG", "entry_ts": 1784059200000, "planned_exit_ts": 1784122500000, "entry_px": 136.25, "exit_px": 139.2475, "size": 33.58, "pnl_usd": 0.69, "net_pct": 2.05, "outcome": "WIN", "edge": 63, "hold_min": 1055, "rsi_1h": 42.73, "rsi_15m": 25.58, "exit_ts": 1784122500000}, {"symbol": "MUBUSDT", "side": "LONG", "entry_ts": 1784106000000, "planned_exit_ts": 1784122200000, "entry_px": 974.82, "exit_px": 966.0466, "size": 31.92, "pnl_usd": -0.34, "net_pct": -1.05, "outcome": "LOSS", "edge": 63, "hold_min": 270, "rsi_1h": 42.02, "rsi_15m": 31.5, "exit_ts": 1784122200000}, {"symbol": "SNDKBUSDT", "side": "LONG", "entry_ts": 1784103300000, "planned_exit_ts": 1784111160000, "entry_px": 1733.12, "exit_px": 1717.5219, "size": 33.75, "pnl_usd": -0.35, "net_pct": -1.05, "outcome": "LOSS", "edge": 63, "hold_min": 131, "rsi_1h": 42.28, "rsi_15m": 28.87, "exit_ts": 1784111160000}, {"symbol": "QQQBUSDT", "side": "LONG", "entry_ts": 1783987200000, "planned_exit_ts": 1784073600000, "entry_px": 710.0, "exit_px": 721.47, "size": 33.46, "pnl_usd": 0.49, "net_pct": 1.465, "outcome": "TIMEOUT", "edge": 73, "hold_min": 1440, "rsi_1h": 42.33, "rsi_15m": 29.25, "exit_ts": 1784073600000}, {"symbol": "CRCLBUSDT", "side": "LONG", "entry_ts": 1784036700000, "planned_exit_ts": 1784036760000, "entry_px": 60.55, "exit_px": 60.005, "size": 33.7, "pnl_usd": -0.35, "net_pct": -1.05, "outcome": "LOSS", "edge": 73, "hold_min": 1, "rsi_1h": 36.21, "rsi_15m": 29.99, "exit_ts": 1784036760000}, {"symbol": "MUBUSDT", "side": "LONG", "entry_ts": 1783986300000, "planned_exit_ts": 1783988100000, "entry_px": 914.01, "exit_px": 934.1182, "size": 33.46, "pnl_usd": 0.69, "net_pct": 2.05, "outcome": "WIN", "edge": 63, "hold_min": 30, "rsi_1h": 43.83, "rsi_15m": 29.83, "exit_ts": 1783988100000}, {"symbol": "TSLABUSDT", "side": "LONG", "entry_ts": 1783951200000, "planned_exit_ts": 1783969980000, "entry_px": 396.09, "exit_px": 392.5252, "size": 33.82, "pnl_usd": -0.36, "net_pct": -1.05, "outcome": "LOSS", "edge": 73, "hold_min": 313, "rsi_1h": 30.5, "rsi_15m": 24.44, "exit_ts": 1783969980000}, {"symbol": "NVDABUSDT", "side": "LONG", "entry_ts": 1783929600000, "planned_exit_ts": 1783960560000, "entry_px": 206.68, "exit_px": 204.8199, "size": 33.82, "pnl_usd": -0.36, "net_pct": -1.05, "outcome": "LOSS", "edge": 63, "hold_min": 516, "rsi_1h": 38.52, "rsi_15m": 34.76, "exit_ts": 1783960560000}, {"symbol": "CRCLBUSDT", "side": "LONG", "entry_ts": 1783952100000, "planned_exit_ts": 1783952160000, "entry_px": 63.85, "exit_px": 63.2754, "size": 31.83, "pnl_usd": -0.33, "net_pct": -1.05, "outcome": "LOSS", "edge": 73, "hold_min": 1, "rsi_1h": 39.67, "rsi_15m": 27.43, "exit_ts": 1783952160000}, {"symbol": "NVDABUSDT", "side": "LONG", "entry_ts": 1783907100000, "planned_exit_ts": 1783920540000, "entry_px": 208.94, "exit_px": 207.0595, "size": 33.94, "pnl_usd": -0.36, "net_pct": -1.05, "outcome": "LOSS", "edge": 63, "hold_min": 224, "rsi_1h": 31.28, "rsi_15m": 29.79, "exit_ts": 1783920540000}, {"symbol": "TSLABUSDT", "side": "LONG", "entry_ts": 1783880100000, "planned_exit_ts": 1783904940000, "entry_px": 407.61, "exit_px": 403.9415, "size": 34.42, "pnl_usd": -0.36, "net_pct": -1.05, "outcome": "LOSS", "edge": 63, "hold_min": 414, "rsi_1h": 43.89, "rsi_15m": 37.99, "exit_ts": 1783904940000}, {"symbol": "MUBUSDT", "side": "LONG", "entry_ts": 1783894500000, "planned_exit_ts": 1783903980000, "entry_px": 970.37, "exit_px": 961.6367, "size": 34.42, "pnl_usd": -0.36, "net_pct": -1.05, "outcome": "LOSS", "edge": 73, "hold_min": 158, "rsi_1h": 43.59, "rsi_15m": 23.37, "exit_ts": 1783903980000}, {"symbol": "CRCLBUSDT", "side": "LONG", "entry_ts": 1783898100000, "planned_exit_ts": 1783903200000, "entry_px": 66.58, "exit_px": 65.9808, "size": 32.05, "pnl_usd": -0.34, "net_pct": -1.05, "outcome": "LOSS", "edge": 63, "hold_min": 85, "rsi_1h": 38.18, "rsi_15m": 37.0, "exit_ts": 1783903200000}, {"symbol": "SNDKBUSDT", "side": "LONG", "entry_ts": 1783895400000, "planned_exit_ts": 1783897260000, "entry_px": 1938.41, "exit_px": 1920.9643, "size": 32.39, "pnl_usd": -0.34, "net_pct": -1.05, "outcome": "LOSS", "edge": 63, "hold_min": 31, "rsi_1h": 41.51, "rsi_15m": 34.72, "exit_ts": 1783897260000}, {"symbol": "NVDABUSDT", "side": "LONG", "entry_ts": 1783779300000, "planned_exit_ts": 1783865700000, "entry_px": 209.53, "exit_px": 211.69, "size": 34.55, "pnl_usd": 0.3, "net_pct": 0.881, "outcome": "TIMEOUT", "edge": 68, "hold_min": 1440, "rsi_1h": 34.81, "rsi_15m": 26.24, "exit_ts": 1783865700000}, {"symbol": "MUBUSDT", "side": "LONG", "entry_ts": 1783811700000, "planned_exit_ts": 1783846320000, "entry_px": 976.5, "exit_px": 967.7115, "size": 32.53, "pnl_usd": -0.34, "net_pct": -1.05, "outcome": "LOSS", "edge": 78, "hold_min": 577, "rsi_1h": 36.78, "rsi_15m": 23.86, "exit_ts": 1783846320000}, {"symbol": "MSTRBUSDT", "side": "LONG", "entry_ts": 1783810800000, "planned_exit_ts": 1783815240000, "entry_px": 95.61, "exit_px": 94.7495, "size": 34.55, "pnl_usd": -0.36, "net_pct": -1.05, "outcome": "LOSS", "edge": 63, "hold_min": 74, "rsi_1h": 38.48, "rsi_15m": 28.22, "exit_ts": 1783815240000}, {"symbol": "SPCXBUSDT", "side": "LONG", "entry_ts": 1783695600000, "planned_exit_ts": 1783713300000, "entry_px": 148.08, "exit_px": 146.7473, "size": 34.81, "pnl_usd": -0.37, "net_pct": -1.05, "outcome": "LOSS", "edge": 63, "hold_min": 295, "rsi_1h": 31.46, "rsi_15m": 26.62, "exit_ts": 1783713300000}, {"symbol": "MSTRBUSDT", "side": "LONG", "entry_ts": 1783695600000, "planned_exit_ts": 1783698120000, "entry_px": 94.9, "exit_px": 94.0459, "size": 34.81, "pnl_usd": -0.37, "net_pct": -1.05, "outcome": "LOSS", "edge": 63, "hold_min": 42, "rsi_1h": 41.41, "rsi_15m": 27.71, "exit_ts": 1783698120000}, {"symbol": "NVDABUSDT", "side": "LONG", "entry_ts": 1783669500000, "planned_exit_ts": 1783691280000, "entry_px": 201.39, "exit_px": 205.8206, "size": 34.23, "pnl_usd": 0.7, "net_pct": 2.05, "outcome": "WIN", "edge": 63, "hold_min": 363, "rsi_1h": 37.69, "rsi_15m": 31.74, "exit_ts": 1783691280000}, {"symbol": "MUBUSDT", "side": "LONG", "entry_ts": 1783688400000, "planned_exit_ts": 1783690200000, "entry_px": 969.01, "exit_px": 960.2889, "size": 34.69, "pnl_usd": -0.36, "net_pct": -1.05, "outcome": "LOSS", "edge": 63, "hold_min": 30, "rsi_1h": 34.82, "rsi_15m": 37.31, "exit_ts": 1783690200000}, {"symbol": "MUBUSDT", "side": "LONG", "entry_ts": 1783667700000, "planned_exit_ts": 1783682160000, "entry_px": 968.18, "exit_px": 989.48, "size": 34.23, "pnl_usd": 0.7, "net_pct": 2.05, "outcome": "WIN", "edge": 73, "hold_min": 241, "rsi_1h": 42.03, "rsi_15m": 24.66, "exit_ts": 1783682160000}, {"symbol": "SNDKBUSDT", "side": "LONG", "entry_ts": 1783671300000, "planned_exit_ts": 1783676700000, "entry_px": 1787.46, "exit_px": 1826.7841, "size": 32.21, "pnl_usd": 0.66, "net_pct": 2.05, "outcome": "WIN", "edge": 68, "hold_min": 90, "rsi_1h": 42.8, "rsi_15m": 25.3, "exit_ts": 1783676700000}, {"symbol": "MUBUSDT", "side": "LONG", "entry_ts": 1783664100000, "planned_exit_ts": 1783664520000, "entry_px": 974.65, "exit_px": 965.8782, "size": 34.35, "pnl_usd": -0.36, "net_pct": -1.05, "outcome": "LOSS", "edge": 63, "hold_min": 7, "rsi_1h": 42.33, "rsi_15m": 27.14, "exit_ts": 1783664520000}, {"symbol": "CRCLBUSDT", "side": "LONG", "entry_ts": 1783608300000, "planned_exit_ts": 1783609620000, "entry_px": 62.45, "exit_px": 63.8239, "size": 34.11, "pnl_usd": 0.7, "net_pct": 2.05, "outcome": "WIN", "edge": 63, "hold_min": 22, "rsi_1h": 43.16, "rsi_15m": 27.82, "exit_ts": 1783609620000}, {"symbol": "NVDABUSDT", "side": "LONG", "entry_ts": 1783605600000, "planned_exit_ts": 1783606140000, "entry_px": 202.26, "exit_px": 200.4397, "size": 34.23, "pnl_usd": -0.36, "net_pct": -1.05, "outcome": "LOSS", "edge": 68, "hold_min": 9, "rsi_1h": 43.3, "rsi_15m": 29.99, "exit_ts": 1783606140000}, {"symbol": "QQQBUSDT", "side": "LONG", "entry_ts": 1783499400000, "planned_exit_ts": 1783585800000, "entry_px": 703.58, "exit_px": 717.54, "size": 31.7, "pnl_usd": 0.58, "net_pct": 1.834, "outcome": "TIMEOUT", "edge": 63, "hold_min": 1440, "rsi_1h": 33.06, "rsi_15m": 28.85, "exit_ts": 1783585800000}, {"symbol": "CRCLBUSDT", "side": "LONG", "entry_ts": 1783522800000, "planned_exit_ts": 1783531800000, "entry_px": 62.41, "exit_px": 63.783, "size": 33.92, "pnl_usd": 0.7, "net_pct": 2.05, "outcome": "WIN", "edge": 63, "hold_min": 150, "rsi_1h": 36.12, "rsi_15m": 27.24, "exit_ts": 1783531800000}, {"symbol": "SPCXBUSDT", "side": "LONG", "entry_ts": 1783454400000, "planned_exit_ts": 1783525500000, "entry_px": 149.8, "exit_px": 148.4518, "size": 33.93, "pnl_usd": -0.36, "net_pct": -1.05, "outcome": "LOSS", "edge": 63, "hold_min": 1185, "rsi_1h": 35.42, "rsi_15m": 28.35, "exit_ts": 1783525500000}, {"symbol": "MUBUSDT", "side": "LONG", "entry_ts": 1783503000000, "planned_exit_ts": 1783505940000, "entry_px": 880.76, "exit_px": 900.1367, "size": 33.45, "pnl_usd": 0.69, "net_pct": 2.05, "outcome": "WIN", "edge": 73, "hold_min": 49, "rsi_1h": 37.92, "rsi_15m": 25.66, "exit_ts": 1783505940000}, {"symbol": "MUBUSDT", "side": "LONG", "entry_ts": 1783499400000, "planned_exit_ts": 1783499760000, "entry_px": 893.25, "exit_px": 885.2107, "size": 33.81, "pnl_usd": -0.36, "net_pct": -1.05, "outcome": "LOSS", "edge": 63, "hold_min": 6, "rsi_1h": 37.72, "rsi_15m": 29.75, "exit_ts": 1783499760000}, {"symbol": "CRCLBUSDT", "side": "LONG", "entry_ts": 1783452600000, "planned_exit_ts": 1783499100000, "entry_px": 64.97, "exit_px": 64.3853, "size": 33.93, "pnl_usd": -0.36, "net_pct": -1.05, "outcome": "LOSS", "edge": 73, "hold_min": 775, "rsi_1h": 30.94, "rsi_15m": 29.31, "exit_ts": 1783499100000}, {"symbol": "SPCXBUSDT", "side": "LONG", "entry_ts": 1783436400000, "planned_exit_ts": 1783451220000, "entry_px": 151.86, "exit_px": 150.4933, "size": 31.94, "pnl_usd": -0.34, "net_pct": -1.05, "outcome": "LOSS", "edge": 63, "hold_min": 247, "rsi_1h": 34.3, "rsi_15m": 29.23, "exit_ts": 1783451220000}, {"symbol": "CRCLBUSDT", "side": "LONG", "entry_ts": 1783433700000, "planned_exit_ts": 1783440300000, "entry_px": 65.54, "exit_px": 66.9819, "size": 33.93, "pnl_usd": 0.7, "net_pct": 2.05, "outcome": "WIN", "edge": 73, "hold_min": 110, "rsi_1h": 36.81, "rsi_15m": 25.06, "exit_ts": 1783440300000}, {"symbol": "TSLABUSDT", "side": "LONG", "entry_ts": 1783433700000, "planned_exit_ts": 1783438800000, "entry_px": 408.79, "exit_px": 405.1109, "size": 33.93, "pnl_usd": -0.36, "net_pct": -1.05, "outcome": "LOSS", "edge": 63, "hold_min": 85, "rsi_1h": 34.59, "rsi_15m": 25.56, "exit_ts": 1783438800000}, {"symbol": "SPCXBUSDT", "side": "LONG", "entry_ts": 1783432800000, "planned_exit_ts": 1783433400000, "entry_px": 153.51, "exit_px": 152.1284, "size": 34.05, "pnl_usd": -0.36, "net_pct": -1.05, "outcome": "LOSS", "edge": 63, "hold_min": 10, "rsi_1h": 35.33, "rsi_15m": 26.95, "exit_ts": 1783433400000}, {"symbol": "QQQBUSDT", "side": "LONG", "entry_ts": 1783395000000, "planned_exit_ts": 1783432440000, "entry_px": 717.2, "exit_px": 710.7452, "size": 32.01, "pnl_usd": -0.34, "net_pct": -1.05, "outcome": "LOSS", "edge": 63, "hold_min": 624, "rsi_1h": 36.82, "rsi_15m": 28.64, "exit_ts": 1783432440000}, {"symbol": "NVDABUSDT", "side": "LONG", "entry_ts": 1783344600000, "planned_exit_ts": 1783420740000, "entry_px": 194.62, "exit_px": 192.8684, "size": 34.8, "pnl_usd": -0.37, "net_pct": -1.05, "outcome": "LOSS", "edge": 71, "hold_min": 1269, "rsi_1h": 44.95, "rsi_15m": 36.8, "exit_ts": 1783420740000}, {"symbol": "MSTRBUSDT", "side": "LONG", "entry_ts": 1783393200000, "planned_exit_ts": 1783401180000, "entry_px": 99.03, "exit_px": 98.1387, "size": 34.42, "pnl_usd": -0.36, "net_pct": -1.05, "outcome": "LOSS", "edge": 63, "hold_min": 133, "rsi_1h": 35.31, "rsi_15m": 29.0, "exit_ts": 1783401180000}, {"symbol": "QQQBUSDT", "side": "LONG", "entry_ts": 1783301400000, "planned_exit_ts": 1783387800000, "entry_px": 720.32, "exit_px": 718.85, "size": 35.29, "pnl_usd": -0.12, "net_pct": -0.354, "outcome": "TIMEOUT", "edge": 63, "hold_min": 1440, "rsi_1h": 34.97, "rsi_15m": 28.05, "exit_ts": 1783387800000}, {"symbol": "SNDKBUSDT", "side": "LONG", "entry_ts": 1783378800000, "planned_exit_ts": 1783381560000, "entry_px": 1707.5, "exit_px": 1692.1325, "size": 31.59, "pnl_usd": -0.33, "net_pct": -1.05, "outcome": "LOSS", "edge": 63, "hold_min": 46, "rsi_1h": 30.31, "rsi_15m": 28.06, "exit_ts": 1783381560000}, {"symbol": "SPCXBUSDT", "side": "LONG", "entry_ts": 1783362600000, "planned_exit_ts": 1783366380000, "entry_px": 156.9, "exit_px": 155.4879, "size": 31.93, "pnl_usd": -0.34, "net_pct": -1.05, "outcome": "LOSS", "edge": 63, "hold_min": 63, "rsi_1h": 31.73, "rsi_15m": 28.99, "exit_ts": 1783366380000}, {"symbol": "SPCXBUSDT", "side": "LONG", "entry_ts": 1783351800000, "planned_exit_ts": 1783359600000, "entry_px": 160.37, "exit_px": 158.9267, "size": 32.27, "pnl_usd": -0.34, "net_pct": -1.05, "outcome": "LOSS", "edge": 63, "hold_min": 130, "rsi_1h": 42.37, "rsi_15m": 28.81, "exit_ts": 1783359600000}, {"symbol": "CRCLBUSDT", "side": "LONG", "entry_ts": 1783342800000, "planned_exit_ts": 1783344000000, "entry_px": 65.29, "exit_px": 64.7024, "size": 35.04, "pnl_usd": -0.37, "net_pct": -1.05, "outcome": "LOSS", "edge": 68, "hold_min": 20, "rsi_1h": 41.26, "rsi_15m": 29.19, "exit_ts": 1783344000000}, {"symbol": "MSTRBUSDT", "side": "LONG", "entry_ts": 1783342800000, "planned_exit_ts": 1783342920000, "entry_px": 97.16, "exit_px": 96.2856, "size": 32.74, "pnl_usd": -0.34, "net_pct": -1.05, "outcome": "LOSS", "edge": 93, "hold_min": 2, "rsi_1h": 32.19, "rsi_15m": 15.74, "exit_ts": 1783342920000}, {"symbol": "CRCLBUSDT", "side": "LONG", "entry_ts": 1783304100000, "planned_exit_ts": 1783339200000, "entry_px": 66.81, "exit_px": 66.2087, "size": 33.21, "pnl_usd": -0.35, "net_pct": -1.05, "outcome": "LOSS", "edge": 63, "hold_min": 585, "rsi_1h": 36.43, "rsi_15m": 28.71, "exit_ts": 1783339200000}, {"symbol": "NVDABUSDT", "side": "LONG", "entry_ts": 1783296900000, "planned_exit_ts": 1783318200000, "entry_px": 196.36, "exit_px": 194.5928, "size": 35.29, "pnl_usd": -0.37, "net_pct": -1.05, "outcome": "LOSS", "edge": 83, "hold_min": 355, "rsi_1h": 31.29, "rsi_15m": 19.15, "exit_ts": 1783318200000}, {"symbol": "MSTRBUSDT", "side": "LONG", "entry_ts": 1783256400000, "planned_exit_ts": 1783277760000, "entry_px": 103.97, "exit_px": 106.2573, "size": 35.04, "pnl_usd": 0.72, "net_pct": 2.05, "outcome": "WIN", "edge": 88, "hold_min": 356, "rsi_1h": 32.75, "rsi_15m": 19.66, "exit_ts": 1783277760000}, {"symbol": "MSTRBUSDT", "side": "LONG", "entry_ts": 1783245600000, "planned_exit_ts": 1783252620000, "entry_px": 105.36, "exit_px": 104.4118, "size": 35.17, "pnl_usd": -0.37, "net_pct": -1.05, "outcome": "LOSS", "edge": 68, "hold_min": 117, "rsi_1h": 36.15, "rsi_15m": 28.67, "exit_ts": 1783252620000}, {"symbol": "CRCLBUSDT", "side": "LONG", "entry_ts": 1783167300000, "planned_exit_ts": 1783215660000, "entry_px": 66.41, "exit_px": 67.871, "size": 34.92, "pnl_usd": 0.72, "net_pct": 2.05, "outcome": "WIN", "edge": 78, "hold_min": 806, "rsi_1h": 40.3, "rsi_15m": 24.5, "exit_ts": 1783215660000}, {"symbol": "NVDABUSDT", "side": "LONG", "entry_ts": 1783011600000, "planned_exit_ts": 1783098000000, "entry_px": 193.45, "exit_px": 196.87, "size": 34.35, "pnl_usd": 0.56, "net_pct": 1.618, "outcome": "TIMEOUT", "edge": 63, "hold_min": 1440, "rsi_1h": 30.64, "rsi_15m": 29.11, "exit_ts": 1783098000000}, {"symbol": "QQQBUSDT", "side": "LONG", "entry_ts": 1783010700000, "planned_exit_ts": 1783097100000, "entry_px": 712.5, "exit_px": 723.1, "size": 34.35, "pnl_usd": 0.46, "net_pct": 1.338, "outcome": "TIMEOUT", "edge": 73, "hold_min": 1440, "rsi_1h": 31.83, "rsi_15m": 29.27, "exit_ts": 1783097100000}, {"symbol": "MUBUSDT", "side": "LONG", "entry_ts": 1783015200000, "planned_exit_ts": 1783018260000, "entry_px": 958.96, "exit_px": 980.0571, "size": 32.34, "pnl_usd": 0.66, "net_pct": 2.05, "outcome": "WIN", "edge": 63, "hold_min": 51, "rsi_1h": 38.21, "rsi_15m": 27.81, "exit_ts": 1783018260000}, {"symbol": "SNDKBUSDT", "side": "LONG", "entry_ts": 1783003500000, "planned_exit_ts": 1783003680000, "entry_px": 1856.72, "exit_px": 1840.0095, "size": 34.48, "pnl_usd": -0.36, "net_pct": -1.05, "outcome": "LOSS", "edge": 63, "hold_min": 3, "rsi_1h": 31.45, "rsi_15m": 27.15, "exit_ts": 1783003680000}, {"symbol": "NVDABUSDT", "side": "LONG", "entry_ts": 1782976500000, "planned_exit_ts": 1783000920000, "entry_px": 195.8, "exit_px": 200.1076, "size": 34.0, "pnl_usd": 0.7, "net_pct": 2.05, "outcome": "WIN", "edge": 63, "hold_min": 407, "rsi_1h": 35.85, "rsi_15m": 26.42, "exit_ts": 1783000920000}, {"symbol": "SNDKBUSDT", "side": "LONG", "entry_ts": 1782980100000, "planned_exit_ts": 1782982320000, "entry_px": 1940.04, "exit_px": 1982.7209, "size": 34.0, "pnl_usd": 0.7, "net_pct": 2.05, "outcome": "WIN", "edge": 73, "hold_min": 37, "rsi_1h": 31.83, "rsi_15m": 29.69, "exit_ts": 1782982320000}], "equity_curve": [{"ts": 1782934428095, "equity": 100.0, "realized": 0.0}, {"ts": 1782982320000, "equity": 100.7, "realized": 0.7}, {"ts": 1783000920000, "equity": 101.4, "realized": 1.4}, {"ts": 1783003680000, "equity": 101.04, "realized": 1.04}, {"ts": 1783018260000, "equity": 101.7, "realized": 1.7}, {"ts": 1783097100000, "equity": 102.16, "realized": 2.16}, {"ts": 1783098000000, "equity": 102.72, "realized": 2.72}, {"ts": 1783215660000, "equity": 103.44, "realized": 3.44}, {"ts": 1783252620000, "equity": 103.07, "realized": 3.07}, {"ts": 1783277760000, "equity": 103.79, "realized": 3.79}, {"ts": 1783318200000, "equity": 103.42, "realized": 3.42}, {"ts": 1783339200000, "equity": 103.07, "realized": 3.07}, {"ts": 1783342920000, "equity": 102.73, "realized": 2.73}, {"ts": 1783344000000, "equity": 102.36, "realized": 2.36}, {"ts": 1783359600000, "equity": 102.02, "realized": 2.02}, {"ts": 1783366380000, "equity": 101.68, "realized": 1.68}, {"ts": 1783381560000, "equity": 101.35, "realized": 1.35}, {"ts": 1783387800000, "equity": 101.23, "realized": 1.23}, {"ts": 1783401180000, "equity": 100.87, "realized": 0.87}, {"ts": 1783420740000, "equity": 100.5, "realized": 0.5}, {"ts": 1783432440000, "equity": 100.16, "realized": 0.16}, {"ts": 1783433400000, "equity": 99.8, "realized": -0.2}, {"ts": 1783438800000, "equity": 99.44, "realized": -0.56}, {"ts": 1783440300000, "equity": 100.14, "realized": 0.14}, {"ts": 1783451220000, "equity": 99.8, "realized": -0.2}, {"ts": 1783499100000, "equity": 99.44, "realized": -0.56}, {"ts": 1783499760000, "equity": 99.08, "realized": -0.92}, {"ts": 1783505940000, "equity": 99.77, "realized": -0.23}, {"ts": 1783525500000, "equity": 99.41, "realized": -0.59}, {"ts": 1783531800000, "equity": 100.11, "realized": 0.11}, {"ts": 1783585800000, "equity": 100.69, "realized": 0.69}, {"ts": 1783606140000, "equity": 100.33, "realized": 0.33}, {"ts": 1783609620000, "equity": 101.03, "realized": 1.03}, {"ts": 1783664520000, "equity": 100.67, "realized": 0.67}, {"ts": 1783676700000, "equity": 101.33, "realized": 1.33}, {"ts": 1783682160000, "equity": 102.03, "realized": 2.03}, {"ts": 1783690200000, "equity": 101.67, "realized": 1.67}, {"ts": 1783691280000, "equity": 102.37, "realized": 2.37}, {"ts": 1783698120000, "equity": 102.0, "realized": 2.0}, {"ts": 1783713300000, "equity": 101.63, "realized": 1.63}, {"ts": 1783815240000, "equity": 101.27, "realized": 1.27}, {"ts": 1783846320000, "equity": 100.93, "realized": 0.93}, {"ts": 1783865700000, "equity": 101.23, "realized": 1.23}, {"ts": 1783897260000, "equity": 100.89, "realized": 0.89}, {"ts": 1783903200000, "equity": 100.55, "realized": 0.55}, {"ts": 1783903980000, "equity": 100.19, "realized": 0.19}, {"ts": 1783904940000, "equity": 99.83, "realized": -0.17}, {"ts": 1783920540000, "equity": 99.47, "realized": -0.53}, {"ts": 1783952160000, "equity": 99.14, "realized": -0.86}, {"ts": 1783960560000, "equity": 98.78, "realized": -1.22}, {"ts": 1783969980000, "equity": 98.42, "realized": -1.58}, {"ts": 1783988100000, "equity": 99.11, "realized": -0.89}, {"ts": 1784036760000, "equity": 98.76, "realized": -1.24}, {"ts": 1784073600000, "equity": 99.25, "realized": -0.75}, {"ts": 1784111160000, "equity": 98.9, "realized": -1.1}, {"ts": 1784122200000, "equity": 98.56, "realized": -1.44}, {"ts": 1784122500000, "equity": 99.25, "realized": -0.75}, {"ts": 1784131500000, "equity": 98.9, "realized": -1.1}, {"ts": 1784137620000, "equity": 99.55, "realized": -0.45}, {"ts": 1784137740000, "equity": 100.24, "realized": 0.24}, {"ts": 1784189520000, "equity": 99.88, "realized": -0.12}, {"ts": 1784205840000, "equity": 99.54, "realized": -0.46}, {"ts": 1784208720000, "equity": 100.19, "realized": 0.19}, {"ts": 1784209500000, "equity": 99.83, "realized": -0.17}, {"ts": 1784210100000, "equity": 99.48, "realized": -0.52}, {"ts": 1784211060000, "equity": 100.18, "realized": 0.18}, {"ts": 1784276220000, "equity": 99.84, "realized": -0.16}, {"ts": 1784479500000, "equity": 100.19, "realized": 0.19}], "timeframes": ["1m", "5m", "1h", "4h", "1d"], "nav_series": {"1m": [{"ts": 1784463911075, "nav": 100.31}, {"ts": 1784463971075, "nav": 100.31}, {"ts": 1784464031075, "nav": 100.3}, {"ts": 1784464091075, "nav": 100.29}, {"ts": 1784464151075, "nav": 100.31}, {"ts": 1784464211075, "nav": 100.31}, {"ts": 1784464271075, "nav": 100.31}, {"ts": 1784464331075, "nav": 100.34}, {"ts": 1784464391075, "nav": 100.34}, {"ts": 1784464451075, "nav": 100.34}, {"ts": 1784464511075, "nav": 100.34}, {"ts": 1784464571075, "nav": 100.34}, {"ts": 1784464631075, "nav": 100.34}, {"ts": 1784464691075, "nav": 100.32}, {"ts": 1784464751075, "nav": 100.32}, {"ts": 1784464811075, "nav": 100.32}, {"ts": 1784464871075, "nav": 100.32}, {"ts": 1784464931075, "nav": 100.32}, {"ts": 1784464991075, "nav": 100.32}, {"ts": 1784465051075, "nav": 100.35}, {"ts": 1784465111075, "nav": 100.35}, {"ts": 1784465171075, "nav": 100.32}, {"ts": 1784465231075, "nav": 100.33}, {"ts": 1784465291075, "nav": 100.33}, {"ts": 1784465351075, "nav": 100.32}, {"ts": 1784465411075, "nav": 100.31}, {"ts": 1784465471075, "nav": 100.31}, {"ts": 1784465531075, "nav": 100.31}, {"ts": 1784465591075, "nav": 100.31}, {"ts": 1784465651075, "nav": 100.31}, {"ts": 1784465711075, "nav": 100.32}, {"ts": 1784465771075, "nav": 100.33}, {"ts": 1784465831075, "nav": 100.32}, {"ts": 1784465891075, "nav": 100.32}, {"ts": 1784465951075, "nav": 100.31}, {"ts": 1784466011075, "nav": 100.31}, {"ts": 1784466071075, "nav": 100.31}, {"ts": 1784466131075, "nav": 100.32}, {"ts": 1784466191075, "nav": 100.32}, {"ts": 1784466251075, "nav": 100.31}, {"ts": 1784466311075, "nav": 100.32}, {"ts": 1784466371075, "nav": 100.3}, {"ts": 1784466431075, "nav": 100.31}, {"ts": 1784466491075, "nav": 100.31}, {"ts": 1784466551075, "nav": 100.31}, {"ts": 1784466611075, "nav": 100.32}, {"ts": 1784466671075, "nav": 100.32}, {"ts": 1784466731075, "nav": 100.32}, {"ts": 1784466791075, "nav": 100.35}, {"ts": 1784466851075, "nav": 100.36}, {"ts": 1784466911075, "nav": 100.36}, {"ts": 1784466971075, "nav": 100.36}, {"ts": 1784467031075, "nav": 100.36}, {"ts": 1784467091075, "nav": 100.36}, {"ts": 1784467151075, "nav": 100.39}, {"ts": 1784467211075, "nav": 100.4}, {"ts": 1784467271075, "nav": 100.39}, {"ts": 1784467331075, "nav": 100.39}, {"ts": 1784467391075, "nav": 100.39}, {"ts": 1784467451075, "nav": 100.39}, {"ts": 1784467511075, "nav": 100.37}, {"ts": 1784467571075, "nav": 100.38}, {"ts": 1784467631075, "nav": 100.38}, {"ts": 1784467691075, "nav": 100.38}, {"ts": 1784467751075, "nav": 100.38}, {"ts": 1784467811075, "nav": 100.41}, {"ts": 1784467871075, "nav": 100.41}, {"ts": 1784467931075, "nav": 100.39}, {"ts": 1784467991075, "nav": 100.39}, {"ts": 1784468051075, "nav": 100.4}, {"ts": 1784468111075, "nav": 100.4}, {"ts": 1784468171075, "nav": 100.4}, {"ts": 1784468231075, "nav": 100.4}, {"ts": 1784468291075, "nav": 100.4}, {"ts": 1784468351075, "nav": 100.41}, {"ts": 1784468411075, "nav": 100.4}, {"ts": 1784468471075, "nav": 100.4}, {"ts": 1784468531075, "nav": 100.43}, {"ts": 1784468591075, "nav": 100.4}, {"ts": 1784468651075, "nav": 100.41}, {"ts": 1784468711075, "nav": 100.41}, {"ts": 1784468771075, "nav": 100.41}, {"ts": 1784468831075, "nav": 100.41}, {"ts": 1784468891075, "nav": 100.41}, {"ts": 1784468951075, "nav": 100.41}, {"ts": 1784469011075, "nav": 100.42}, {"ts": 1784469071075, "nav": 100.42}, {"ts": 1784469131075, "nav": 100.42}, {"ts": 1784469191075, "nav": 100.43}, {"ts": 1784469251075, "nav": 100.43}, {"ts": 1784469311075, "nav": 100.43}, {"ts": 1784469371075, "nav": 100.41}, {"ts": 1784469431075, "nav": 100.41}, {"ts": 1784469491075, "nav": 100.41}, {"ts": 1784469551075, "nav": 100.42}, {"ts": 1784469611075, "nav": 100.39}, {"ts": 1784469671075, "nav": 100.4}, {"ts": 1784469731075, "nav": 100.4}, {"ts": 1784469791075, "nav": 100.4}, {"ts": 1784469851075, "nav": 100.4}, {"ts": 1784469911075, "nav": 100.39}, {"ts": 1784469971075, "nav": 100.39}, {"ts": 1784470031075, "nav": 100.39}, {"ts": 1784470091075, "nav": 100.39}, {"ts": 1784470151075, "nav": 100.39}, {"ts": 1784470211075, "nav": 100.4}, {"ts": 1784470271075, "nav": 100.41}, {"ts": 1784470331075, "nav": 100.37}, {"ts": 1784470391075, "nav": 100.37}, {"ts": 1784470451075, "nav": 100.36}, {"ts": 1784470511075, "nav": 100.35}, {"ts": 1784470571075, "nav": 100.36}, {"ts": 1784470631075, "nav": 100.36}, {"ts": 1784470691075, "nav": 100.36}, {"ts": 1784470751075, "nav": 100.39}, {"ts": 1784470811075, "nav": 100.38}, {"ts": 1784470871075, "nav": 100.39}, {"ts": 1784470931075, "nav": 100.34}, {"ts": 1784470991075, "nav": 100.34}, {"ts": 1784471051075, "nav": 100.34}, {"ts": 1784471111075, "nav": 100.34}, {"ts": 1784471171075, "nav": 100.31}, {"ts": 1784471231075, "nav": 100.31}, {"ts": 1784471291075, "nav": 100.34}, {"ts": 1784471351075, "nav": 100.33}, {"ts": 1784471411075, "nav": 100.32}, {"ts": 1784471471075, "nav": 100.32}, {"ts": 1784471531075, "nav": 100.32}, {"ts": 1784471591075, "nav": 100.32}, {"ts": 1784471651075, "nav": 100.32}, {"ts": 1784471711075, "nav": 100.34}, {"ts": 1784471771075, "nav": 100.35}, {"ts": 1784471831075, "nav": 100.35}, {"ts": 1784471891075, "nav": 100.35}, {"ts": 1784471951075, "nav": 100.35}, {"ts": 1784472011075, "nav": 100.34}, {"ts": 1784472071075, "nav": 100.34}, {"ts": 1784472131075, "nav": 100.35}, {"ts": 1784472191075, "nav": 100.35}, {"ts": 1784472251075, "nav": 100.35}, {"ts": 1784472311075, "nav": 100.35}, {"ts": 1784472371075, "nav": 100.36}, {"ts": 1784472431075, "nav": 100.36}, {"ts": 1784472491075, "nav": 100.37}, {"ts": 1784472551075, "nav": 100.38}, {"ts": 1784472611075, "nav": 100.38}, {"ts": 1784472671075, "nav": 100.36}, {"ts": 1784472731075, "nav": 100.32}, {"ts": 1784472791075, "nav": 100.33}, {"ts": 1784472851075, "nav": 100.33}, {"ts": 1784472911075, "nav": 100.34}, {"ts": 1784472971075, "nav": 100.33}, {"ts": 1784473031075, "nav": 100.33}, {"ts": 1784473091075, "nav": 100.33}, {"ts": 1784473151075, "nav": 100.34}, {"ts": 1784473211075, "nav": 100.34}, {"ts": 1784473271075, "nav": 100.34}, {"ts": 1784473331075, "nav": 100.33}, {"ts": 1784473391075, "nav": 100.33}, {"ts": 1784473451075, "nav": 100.33}, {"ts": 1784473511075, "nav": 100.34}, {"ts": 1784473571075, "nav": 100.33}, {"ts": 1784473631075, "nav": 100.33}, {"ts": 1784473691075, "nav": 100.34}, {"ts": 1784473751075, "nav": 100.33}, {"ts": 1784473811075, "nav": 100.33}, {"ts": 1784473871075, "nav": 100.35}, {"ts": 1784473931075, "nav": 100.37}, {"ts": 1784473991075, "nav": 100.37}, {"ts": 1784474051075, "nav": 100.38}, {"ts": 1784474111075, "nav": 100.37}, {"ts": 1784474171075, "nav": 100.37}, {"ts": 1784474231075, "nav": 100.37}, {"ts": 1784474291075, "nav": 100.35}, {"ts": 1784474351075, "nav": 100.35}, {"ts": 1784474411075, "nav": 100.35}, {"ts": 1784474471075, "nav": 100.35}, {"ts": 1784474531075, "nav": 100.35}, {"ts": 1784474591075, "nav": 100.35}, {"ts": 1784474651075, "nav": 100.35}, {"ts": 1784474711075, "nav": 100.37}, {"ts": 1784474771075, "nav": 100.35}, {"ts": 1784474831075, "nav": 100.35}, {"ts": 1784474891075, "nav": 100.36}, {"ts": 1784474951075, "nav": 100.33}, {"ts": 1784475011075, "nav": 100.33}, {"ts": 1784475071075, "nav": 100.33}, {"ts": 1784475131075, "nav": 100.35}, {"ts": 1784475191075, "nav": 100.35}, {"ts": 1784475251075, "nav": 100.35}, {"ts": 1784475311075, "nav": 100.35}, {"ts": 1784475371075, "nav": 100.35}, {"ts": 1784475431075, "nav": 100.33}, {"ts": 1784475491075, "nav": 100.33}, {"ts": 1784475551075, "nav": 100.33}, {"ts": 1784475611075, "nav": 100.33}, {"ts": 1784475671075, "nav": 100.33}, {"ts": 1784475731075, "nav": 100.35}, {"ts": 1784475791075, "nav": 100.35}, {"ts": 1784475851075, "nav": 100.35}, {"ts": 1784475911075, "nav": 100.35}, {"ts": 1784475971075, "nav": 100.34}, {"ts": 1784476031075, "nav": 100.33}, {"ts": 1784476091075, "nav": 100.32}, {"ts": 1784476151075, "nav": 100.33}, {"ts": 1784476211075, "nav": 100.33}, {"ts": 1784476271075, "nav": 100.33}, {"ts": 1784476331075, "nav": 100.33}, {"ts": 1784476391075, "nav": 100.33}, {"ts": 1784476451075, "nav": 100.34}, {"ts": 1784476511075, "nav": 100.34}, {"ts": 1784476571075, "nav": 100.33}, {"ts": 1784476631075, "nav": 100.33}, {"ts": 1784476691075, "nav": 100.33}, {"ts": 1784476751075, "nav": 100.33}, {"ts": 1784476811075, "nav": 100.33}, {"ts": 1784476871075, "nav": 100.35}, {"ts": 1784476931075, "nav": 100.35}, {"ts": 1784476991075, "nav": 100.34}, {"ts": 1784477051075, "nav": 100.34}, {"ts": 1784477111075, "nav": 100.35}, {"ts": 1784477171075, "nav": 100.33}, {"ts": 1784477231075, "nav": 100.24}, {"ts": 1784477291075, "nav": 100.27}, {"ts": 1784477351075, "nav": 100.27}, {"ts": 1784477411075, "nav": 100.26}, {"ts": 1784477471075, "nav": 100.25}, {"ts": 1784477531075, "nav": 100.24}, {"ts": 1784477591075, "nav": 100.27}, {"ts": 1784477651075, "nav": 100.26}, {"ts": 1784477711075, "nav": 100.22}, {"ts": 1784477771075, "nav": 100.21}, {"ts": 1784477831075, "nav": 100.23}, {"ts": 1784477891075, "nav": 100.21}, {"ts": 1784477951075, "nav": 100.21}, {"ts": 1784478011075, "nav": 100.24}, {"ts": 1784478071075, "nav": 100.24}, {"ts": 1784478131075, "nav": 100.26}, {"ts": 1784478191075, "nav": 100.26}, {"ts": 1784478251075, "nav": 100.26}, {"ts": 1784478311075, "nav": 100.26}, {"ts": 1784478371075, "nav": 100.26}, {"ts": 1784478431075, "nav": 100.24}, {"ts": 1784478491075, "nav": 100.24}, {"ts": 1784478551075, "nav": 100.22}, {"ts": 1784478611075, "nav": 100.26}, {"ts": 1784478671075, "nav": 100.24}, {"ts": 1784478731075, "nav": 100.22}, {"ts": 1784478791075, "nav": 100.22}, {"ts": 1784478851075, "nav": 100.19}, {"ts": 1784478911075, "nav": 100.21}, {"ts": 1784478971075, "nav": 100.21}, {"ts": 1784479031075, "nav": 100.21}, {"ts": 1784479091075, "nav": 100.21}, {"ts": 1784479151075, "nav": 100.21}, {"ts": 1784479211075, "nav": 100.22}, {"ts": 1784479271075, "nav": 100.22}, {"ts": 1784479331075, "nav": 100.22}, {"ts": 1784479391075, "nav": 100.21}, {"ts": 1784479451075, "nav": 100.23}, {"ts": 1784479511075, "nav": 100.19}, {"ts": 1784479571075, "nav": 100.19}, {"ts": 1784479631075, "nav": 100.19}, {"ts": 1784479691075, "nav": 100.19}, {"ts": 1784479751075, "nav": 100.19}, {"ts": 1784479811075, "nav": 100.19}, {"ts": 1784479871075, "nav": 100.19}, {"ts": 1784479931075, "nav": 100.19}, {"ts": 1784479991075, "nav": 100.19}, {"ts": 1784480051075, "nav": 100.19}, {"ts": 1784480111075, "nav": 100.19}, {"ts": 1784480171075, "nav": 100.19}, {"ts": 1784480231075, "nav": 100.19}, {"ts": 1784480291075, "nav": 100.19}, {"ts": 1784480351075, "nav": 100.19}, {"ts": 1784480411075, "nav": 100.19}, {"ts": 1784480471075, "nav": 100.19}, {"ts": 1784480531075, "nav": 100.19}, {"ts": 1784480591075, "nav": 100.19}, {"ts": 1784480651075, "nav": 100.19}, {"ts": 1784480711075, "nav": 100.19}, {"ts": 1784480771075, "nav": 100.19}, {"ts": 1784480831075, "nav": 100.19}, {"ts": 1784480891075, "nav": 100.19}, {"ts": 1784480951075, "nav": 100.19}, {"ts": 1784481011075, "nav": 100.19}, {"ts": 1784481071075, "nav": 100.19}, {"ts": 1784481131075, "nav": 100.19}, {"ts": 1784481191075, "nav": 100.19}, {"ts": 1784481251075, "nav": 100.19}, {"ts": 1784481311075, "nav": 100.19}, {"ts": 1784481371075, "nav": 100.19}, {"ts": 1784481431075, "nav": 100.19}, {"ts": 1784481491075, "nav": 100.19}, {"ts": 1784481551075, "nav": 100.19}, {"ts": 1784481611075, "nav": 100.19}, {"ts": 1784481671075, "nav": 100.19}, {"ts": 1784481731075, "nav": 100.19}, {"ts": 1784481791075, "nav": 100.19}, {"ts": 1784481851075, "nav": 100.19}, {"ts": 1784481911075, "nav": 100.19}, {"ts": 1784481971075, "nav": 100.19}, {"ts": 1784482031075, "nav": 100.19}, {"ts": 1784482091075, "nav": 100.19}, {"ts": 1784482151075, "nav": 100.19}, {"ts": 1784482211075, "nav": 100.19}, {"ts": 1784482271075, "nav": 100.19}, {"ts": 1784482331075, "nav": 100.19}, {"ts": 1784482391075, "nav": 100.19}, {"ts": 1784482451075, "nav": 100.19}, {"ts": 1784482511075, "nav": 100.19}, {"ts": 1784482571075, "nav": 100.19}, {"ts": 1784482631075, "nav": 100.19}, {"ts": 1784482691075, "nav": 100.19}, {"ts": 1784482751075, "nav": 100.19}, {"ts": 1784482811075, "nav": 100.19}, {"ts": 1784482871075, "nav": 100.19}, {"ts": 1784482931075, "nav": 100.19}, {"ts": 1784482991075, "nav": 100.19}, {"ts": 1784483051075, "nav": 100.19}, {"ts": 1784483111075, "nav": 100.16}, {"ts": 1784483171075, "nav": 100.16}, {"ts": 1784483231075, "nav": 100.16}, {"ts": 1784483291075, "nav": 100.16}, {"ts": 1784483351075, "nav": 100.16}, {"ts": 1784483411075, "nav": 100.18}, {"ts": 1784483471075, "nav": 100.18}, {"ts": 1784483531075, "nav": 100.18}, {"ts": 1784483591075, "nav": 100.18}, {"ts": 1784483651075, "nav": 100.18}, {"ts": 1784483711075, "nav": 100.18}, {"ts": 1784483771075, "nav": 100.18}, {"ts": 1784483831075, "nav": 100.18}, {"ts": 1784483891075, "nav": 100.18}, {"ts": 1784483951075, "nav": 100.18}, {"ts": 1784484011075, "nav": 100.15}, {"ts": 1784484071075, "nav": 100.15}, {"ts": 1784484131075, "nav": 100.14}, {"ts": 1784484191075, "nav": 100.12}, {"ts": 1784484251075, "nav": 100.12}, {"ts": 1784484311075, "nav": 100.12}, {"ts": 1784484371075, "nav": 100.12}, {"ts": 1784484431075, "nav": 100.12}, {"ts": 1784484491075, "nav": 100.14}, {"ts": 1784484551075, "nav": 100.1}, {"ts": 1784484611075, "nav": 100.2}, {"ts": 1784484671075, "nav": 100.2}, {"ts": 1784484731075, "nav": 100.2}, {"ts": 1784484791075, "nav": 100.2}, {"ts": 1784484851075, "nav": 100.2}, {"ts": 1784484911075, "nav": 100.2}, {"ts": 1784484971075, "nav": 100.2}, {"ts": 1784485031075, "nav": 100.2}, {"ts": 1784485091075, "nav": 100.2}, {"ts": 1784485151075, "nav": 100.17}, {"ts": 1784485211075, "nav": 100.17}, {"ts": 1784485271075, "nav": 100.17}, {"ts": 1784485331075, "nav": 100.17}, {"ts": 1784485391075, "nav": 100.17}, {"ts": 1784485451075, "nav": 100.17}, {"ts": 1784485511075, "nav": 100.17}, {"ts": 1784485571075, "nav": 100.17}, {"ts": 1784485631075, "nav": 100.17}, {"ts": 1784485691075, "nav": 100.17}, {"ts": 1784485751075, "nav": 100.17}, {"ts": 1784485811075, "nav": 100.17}, {"ts": 1784485871075, "nav": 100.17}, {"ts": 1784485931075, "nav": 100.17}, {"ts": 1784485991075, "nav": 100.15}, {"ts": 1784486051075, "nav": 100.21}, {"ts": 1784486111075, "nav": 100.21}, {"ts": 1784486171075, "nav": 100.21}, {"ts": 1784486231075, "nav": 100.21}, {"ts": 1784486291075, "nav": 100.21}, {"ts": 1784486351075, "nav": 100.21}, {"ts": 1784486411075, "nav": 100.21}, {"ts": 1784486471075, "nav": 100.21}, {"ts": 1784486531075, "nav": 100.21}, {"ts": 1784486591075, "nav": 100.21}, {"ts": 1784486651075, "nav": 100.09}, {"ts": 1784486711075, "nav": 100.09}, {"ts": 1784486771075, "nav": 100.09}, {"ts": 1784486831075, "nav": 100.09}, {"ts": 1784486891075, "nav": 100.09}, {"ts": 1784486951075, "nav": 100.09}, {"ts": 1784487011075, "nav": 100.09}, {"ts": 1784487071075, "nav": 100.13}, {"ts": 1784487131075, "nav": 100.13}, {"ts": 1784487191075, "nav": 100.13}, {"ts": 1784487251075, "nav": 100.13}, {"ts": 1784487311075, "nav": 100.13}, {"ts": 1784487371075, "nav": 100.12}, {"ts": 1784487431075, "nav": 100.13}, {"ts": 1784487491075, "nav": 100.14}, {"ts": 1784487551075, "nav": 100.14}, {"ts": 1784487611075, "nav": 100.14}, {"ts": 1784487671075, "nav": 100.14}, {"ts": 1784487731075, "nav": 100.14}, {"ts": 1784487791075, "nav": 100.14}, {"ts": 1784487851075, "nav": 100.14}, {"ts": 1784487911075, "nav": 100.14}, {"ts": 1784487971075, "nav": 100.16}, {"ts": 1784488031075, "nav": 100.16}, {"ts": 1784488091075, "nav": 100.16}, {"ts": 1784488151075, "nav": 100.16}, {"ts": 1784488211075, "nav": 100.16}, {"ts": 1784488271075, "nav": 100.16}, {"ts": 1784488331075, "nav": 100.16}, {"ts": 1784488391075, "nav": 100.16}, {"ts": 1784488451075, "nav": 100.16}, {"ts": 1784488511075, "nav": 100.16}, {"ts": 1784488571075, "nav": 100.16}, {"ts": 1784488631075, "nav": 100.16}, {"ts": 1784488691075, "nav": 100.16}, {"ts": 1784488751075, "nav": 100.16}, {"ts": 1784488811075, "nav": 100.14}, {"ts": 1784488871075, "nav": 100.14}, {"ts": 1784488931075, "nav": 100.14}, {"ts": 1784488991075, "nav": 100.14}, {"ts": 1784489051075, "nav": 100.14}, {"ts": 1784489111075, "nav": 100.14}, {"ts": 1784489171075, "nav": 100.14}, {"ts": 1784489231075, "nav": 100.14}, {"ts": 1784489291075, "nav": 100.14}, {"ts": 1784489351075, "nav": 100.14}, {"ts": 1784489411075, "nav": 100.14}, {"ts": 1784489471075, "nav": 100.14}, {"ts": 1784489531075, "nav": 100.14}, {"ts": 1784489591075, "nav": 100.14}, {"ts": 1784489651075, "nav": 100.14}, {"ts": 1784489711075, "nav": 100.14}, {"ts": 1784489771075, "nav": 100.14}, {"ts": 1784489831075, "nav": 100.14}, {"ts": 1784489891075, "nav": 100.14}, {"ts": 1784489951075, "nav": 100.14}, {"ts": 1784490011075, "nav": 100.14}, {"ts": 1784490071075, "nav": 100.14}, {"ts": 1784490131075, "nav": 100.1}, {"ts": 1784490191075, "nav": 100.1}, {"ts": 1784490251075, "nav": 100.1}, {"ts": 1784490311075, "nav": 100.09}, {"ts": 1784490371075, "nav": 100.09}, {"ts": 1784490431075, "nav": 100.09}, {"ts": 1784490491075, "nav": 100.09}, {"ts": 1784490551075, "nav": 100.09}, {"ts": 1784490611075, "nav": 100.09}, {"ts": 1784490671075, "nav": 100.09}, {"ts": 1784490731075, "nav": 100.09}, {"ts": 1784490791075, "nav": 100.09}, {"ts": 1784490851075, "nav": 100.09}, {"ts": 1784490911075, "nav": 100.09}, {"ts": 1784490971075, "nav": 100.09}, {"ts": 1784491031075, "nav": 100.09}, {"ts": 1784491091075, "nav": 100.09}, {"ts": 1784491151075, "nav": 100.09}, {"ts": 1784491211075, "nav": 100.09}, {"ts": 1784491271075, "nav": 100.09}, {"ts": 1784491331075, "nav": 100.13}, {"ts": 1784491391075, "nav": 100.12}, {"ts": 1784491451075, "nav": 100.12}, {"ts": 1784491511075, "nav": 100.12}, {"ts": 1784491571075, "nav": 100.12}, {"ts": 1784491631075, "nav": 100.12}, {"ts": 1784491691075, "nav": 100.12}, {"ts": 1784491751075, "nav": 100.05}, {"ts": 1784491811075, "nav": 100.05}, {"ts": 1784491871075, "nav": 100.1}, {"ts": 1784491931075, "nav": 100.09}, {"ts": 1784491991075, "nav": 100.09}, {"ts": 1784492051075, "nav": 100.09}, {"ts": 1784492111075, "nav": 100.1}, {"ts": 1784492171075, "nav": 100.1}, {"ts": 1784492231075, "nav": 100.1}, {"ts": 1784492291075, "nav": 100.1}, {"ts": 1784492351075, "nav": 100.1}, {"ts": 1784492411075, "nav": 100.08}, {"ts": 1784492471075, "nav": 100.09}, {"ts": 1784492531075, "nav": 100.09}, {"ts": 1784492591075, "nav": 100.09}, {"ts": 1784492651075, "nav": 100.09}, {"ts": 1784492711075, "nav": 100.09}, {"ts": 1784492771075, "nav": 100.09}, {"ts": 1784492831075, "nav": 100.09}, {"ts": 1784492891075, "nav": 100.09}, {"ts": 1784492951075, "nav": 100.09}, {"ts": 1784493011075, "nav": 100.09}, {"ts": 1784493071075, "nav": 100.09}, {"ts": 1784493131075, "nav": 100.09}, {"ts": 1784493191075, "nav": 100.09}, {"ts": 1784493251075, "nav": 100.09}, {"ts": 1784493311075, "nav": 100.09}, {"ts": 1784493371075, "nav": 100.09}, {"ts": 1784493431075, "nav": 100.09}, {"ts": 1784493491075, "nav": 100.09}, {"ts": 1784493551075, "nav": 100.09}, {"ts": 1784493611075, "nav": 100.09}, {"ts": 1784493671075, "nav": 100.08}, {"ts": 1784493731075, "nav": 100.08}, {"ts": 1784493791075, "nav": 100.08}, {"ts": 1784493851075, "nav": 100.08}, {"ts": 1784493911075, "nav": 100.08}, {"ts": 1784493971075, "nav": 100.08}, {"ts": 1784494031075, "nav": 100.08}, {"ts": 1784494091075, "nav": 100.08}, {"ts": 1784494151075, "nav": 100.08}, {"ts": 1784494211075, "nav": 100.05}, {"ts": 1784494271075, "nav": 100.02}, {"ts": 1784494331075, "nav": 100.02}, {"ts": 1784494391075, "nav": 100.04}, {"ts": 1784494451075, "nav": 100.06}, {"ts": 1784494511075, "nav": 100.06}, {"ts": 1784494571075, "nav": 100.06}, {"ts": 1784494631075, "nav": 100.06}, {"ts": 1784494691075, "nav": 100.06}, {"ts": 1784494751075, "nav": 100.06}, {"ts": 1784494811075, "nav": 100.07}, {"ts": 1784494871075, "nav": 100.07}, {"ts": 1784494931075, "nav": 100.08}, {"ts": 1784494991075, "nav": 100.08}, {"ts": 1784495051075, "nav": 100.08}, {"ts": 1784495111075, "nav": 100.08}, {"ts": 1784495171075, "nav": 100.06}, {"ts": 1784495231075, "nav": 100.06}, {"ts": 1784495291075, "nav": 100.06}, {"ts": 1784495351075, "nav": 100.06}, {"ts": 1784495411075, "nav": 100.06}, {"ts": 1784495471075, "nav": 100.06}, {"ts": 1784495531075, "nav": 100.06}, {"ts": 1784495591075, "nav": 100.06}, {"ts": 1784495651075, "nav": 100.06}, {"ts": 1784495711075, "nav": 100.06}, {"ts": 1784495771075, "nav": 100.06}, {"ts": 1784495831075, "nav": 100.06}, {"ts": 1784495891075, "nav": 100.06}, {"ts": 1784495951075, "nav": 100.06}, {"ts": 1784496011075, "nav": 100.06}, {"ts": 1784496071075, "nav": 100.06}, {"ts": 1784496131075, "nav": 100.06}, {"ts": 1784496191075, "nav": 100.04}, {"ts": 1784496251075, "nav": 100.04}, {"ts": 1784496311075, "nav": 100.04}, {"ts": 1784496371075, "nav": 100.04}, {"ts": 1784496431075, "nav": 100.04}, {"ts": 1784496491075, "nav": 100.04}, {"ts": 1784496551075, "nav": 100.04}, {"ts": 1784496611075, "nav": 100.04}, {"ts": 1784496671075, "nav": 100.04}, {"ts": 1784496731075, "nav": 100.04}, {"ts": 1784496791075, "nav": 100.04}, {"ts": 1784496851075, "nav": 100.04}, {"ts": 1784496911075, "nav": 100.04}, {"ts": 1784496971075, "nav": 100.05}, {"ts": 1784497031075, "nav": 100.06}, {"ts": 1784497091075, "nav": 100.07}, {"ts": 1784497151075, "nav": 100.09}, {"ts": 1784497211075, "nav": 100.07}, {"ts": 1784497271075, "nav": 100.09}, {"ts": 1784497331075, "nav": 100.1}, {"ts": 1784497391075, "nav": 100.09}, {"ts": 1784497451075, "nav": 100.09}, {"ts": 1784497511075, "nav": 100.09}, {"ts": 1784497571075, "nav": 100.09}, {"ts": 1784497631075, "nav": 100.08}, {"ts": 1784497691075, "nav": 100.07}, {"ts": 1784497751075, "nav": 100.08}, {"ts": 1784497811075, "nav": 100.08}, {"ts": 1784497871075, "nav": 100.07}, {"ts": 1784497931075, "nav": 100.03}, {"ts": 1784497991075, "nav": 100.05}, {"ts": 1784498051075, "nav": 100.05}, {"ts": 1784498111075, "nav": 100.06}, {"ts": 1784498171075, "nav": 100.03}, {"ts": 1784498231075, "nav": 100.04}, {"ts": 1784498291075, "nav": 100.06}, {"ts": 1784498351075, "nav": 100.06}, {"ts": 1784498411075, "nav": 100.08}, {"ts": 1784498471075, "nav": 100.16}, {"ts": 1784498531075, "nav": 100.12}, {"ts": 1784498591075, "nav": 100.16}, {"ts": 1784498651075, "nav": 100.1}, {"ts": 1784498711075, "nav": 100.05}, {"ts": 1784498771075, "nav": 100.01}, {"ts": 1784498831075, "nav": 100.02}, {"ts": 1784498891075, "nav": 100.14}, {"ts": 1784498951075, "nav": 100.14}, {"ts": 1784499011075, "nav": 100.08}, {"ts": 1784499071075, "nav": 100.06}, {"ts": 1784499131075, "nav": 100.06}, {"ts": 1784499191075, "nav": 100.06}, {"ts": 1784499251075, "nav": 100.06}, {"ts": 1784499311075, "nav": 100.37}, {"ts": 1784499371075, "nav": 100.29}, {"ts": 1784499431075, "nav": 100.3}, {"ts": 1784499491075, "nav": 100.27}, {"ts": 1784499551075, "nav": 100.28}, {"ts": 1784499611075, "nav": 100.26}, {"ts": 1784499671075, "nav": 100.32}, {"ts": 1784499731075, "nav": 100.36}, {"ts": 1784499791075, "nav": 100.26}, {"ts": 1784499851075, "nav": 100.3}, {"ts": 1784499911075, "nav": 100.23}, {"ts": 1784499971075, "nav": 100.21}, {"ts": 1784500031075, "nav": 100.25}, {"ts": 1784500091075, "nav": 100.26}, {"ts": 1784500151075, "nav": 100.26}, {"ts": 1784500211075, "nav": 100.25}, {"ts": 1784500271075, "nav": 100.2}, {"ts": 1784500331075, "nav": 100.22}, {"ts": 1784500391075, "nav": 100.3}, {"ts": 1784500451075, "nav": 100.29}, {"ts": 1784500511075, "nav": 100.29}, {"ts": 1784500571075, "nav": 100.29}, {"ts": 1784500631075, "nav": 100.24}, {"ts": 1784500691075, "nav": 100.23}, {"ts": 1784500751075, "nav": 100.28}, {"ts": 1784500811075, "nav": 100.28}, {"ts": 1784500871075, "nav": 100.28}, {"ts": 1784500931075, "nav": 100.28}, {"ts": 1784500991075, "nav": 100.28}, {"ts": 1784501051075, "nav": 100.28}, {"ts": 1784501111075, "nav": 100.28}, {"ts": 1784501171075, "nav": 100.28}, {"ts": 1784501231075, "nav": 100.3}, {"ts": 1784501291075, "nav": 100.3}, {"ts": 1784501351075, "nav": 100.3}, {"ts": 1784501411075, "nav": 100.3}, {"ts": 1784501471075, "nav": 100.3}, {"ts": 1784501531075, "nav": 100.28}, {"ts": 1784501591075, "nav": 100.28}, {"ts": 1784501651075, "nav": 100.28}, {"ts": 1784501711075, "nav": 100.28}, {"ts": 1784501771075, "nav": 100.28}, {"ts": 1784501831075, "nav": 100.28}, {"ts": 1784501891075, "nav": 100.33}, {"ts": 1784501951075, "nav": 100.33}, {"ts": 1784502011075, "nav": 100.27}, {"ts": 1784502071075, "nav": 100.27}, {"ts": 1784502131075, "nav": 100.27}, {"ts": 1784502191075, "nav": 100.27}, {"ts": 1784502251075, "nav": 100.27}, {"ts": 1784502311075, "nav": 100.27}, {"ts": 1784502371075, "nav": 100.33}, {"ts": 1784502431075, "nav": 100.34}, {"ts": 1784502491075, "nav": 100.35}, {"ts": 1784502551075, "nav": 100.37}, {"ts": 1784502611075, "nav": 100.35}, {"ts": 1784502671075, "nav": 100.35}, {"ts": 1784502731075, "nav": 100.41}, {"ts": 1784502791075, "nav": 100.41}, {"ts": 1784502851075, "nav": 100.36}, {"ts": 1784502911075, "nav": 100.36}, {"ts": 1784502971075, "nav": 100.36}, {"ts": 1784503031075, "nav": 100.39}, {"ts": 1784503091075, "nav": 100.38}, {"ts": 1784503151075, "nav": 100.45}, {"ts": 1784503211075, "nav": 100.5}, {"ts": 1784503271075, "nav": 100.49}, {"ts": 1784503331075, "nav": 100.47}, {"ts": 1784503391075, "nav": 100.44}, {"ts": 1784503451075, "nav": 100.5}, {"ts": 1784503511075, "nav": 100.5}, {"ts": 1784503571075, "nav": 100.51}, {"ts": 1784503631075, "nav": 100.51}, {"ts": 1784503691075, "nav": 100.51}, {"ts": 1784503751075, "nav": 100.51}, {"ts": 1784503811075, "nav": 100.49}, {"ts": 1784503871075, "nav": 100.57}, {"ts": 1784503931075, "nav": 100.57}, {"ts": 1784503991075, "nav": 100.57}, {"ts": 1784504051075, "nav": 100.57}, {"ts": 1784504111075, "nav": 100.57}, {"ts": 1784504171075, "nav": 100.51}, {"ts": 1784504231075, "nav": 100.55}, {"ts": 1784504291075, "nav": 100.55}, {"ts": 1784504351075, "nav": 100.55}, {"ts": 1784504411075, "nav": 100.55}, {"ts": 1784504471075, "nav": 100.55}, {"ts": 1784504531075, "nav": 100.55}, {"ts": 1784504591075, "nav": 100.55}, {"ts": 1784504651075, "nav": 100.55}, {"ts": 1784504711075, "nav": 100.53}, {"ts": 1784504771075, "nav": 100.53}, {"ts": 1784504831075, "nav": 100.44}, {"ts": 1784504891075, "nav": 100.46}, {"ts": 1784504951075, "nav": 100.42}, {"ts": 1784505011075, "nav": 100.42}, {"ts": 1784505071075, "nav": 100.42}, {"ts": 1784505131075, "nav": 100.42}, {"ts": 1784505191075, "nav": 100.42}, {"ts": 1784505251075, "nav": 100.42}, {"ts": 1784505311075, "nav": 100.42}, {"ts": 1784505371075, "nav": 100.42}, {"ts": 1784505431075, "nav": 100.42}, {"ts": 1784505491075, "nav": 100.54}, {"ts": 1784505551075, "nav": 100.54}, {"ts": 1784505611075, "nav": 100.42}, {"ts": 1784505671075, "nav": 100.41}, {"ts": 1784505731075, "nav": 100.37}, {"ts": 1784505791075, "nav": 100.37}, {"ts": 1784505851075, "nav": 100.41}, {"ts": 1784505911075, "nav": 100.41}, {"ts": 1784505971075, "nav": 100.57}, {"ts": 1784506031075, "nav": 100.57}, {"ts": 1784506091075, "nav": 100.57}, {"ts": 1784506151075, "nav": 100.7}, {"ts": 1784506211075, "nav": 100.7}, {"ts": 1784506271075, "nav": 100.72}, {"ts": 1784506331075, "nav": 100.72}, {"ts": 1784506391075, "nav": 100.75}, {"ts": 1784506451075, "nav": 100.81}, {"ts": 1784506511075, "nav": 100.78}, {"ts": 1784506571075, "nav": 100.81}, {"ts": 1784506631075, "nav": 100.78}, {"ts": 1784506691075, "nav": 100.78}, {"ts": 1784506751075, "nav": 100.78}, {"ts": 1784506811075, "nav": 100.72}, {"ts": 1784506871075, "nav": 100.72}, {"ts": 1784506931075, "nav": 100.65}, {"ts": 1784506991075, "nav": 100.63}, {"ts": 1784507051075, "nav": 100.63}, {"ts": 1784507111075, "nav": 100.63}], "5m": [{"ts": 1784334311075, "nav": 99.84}, {"ts": 1784334611075, "nav": 99.84}, {"ts": 1784334911075, "nav": 99.84}, {"ts": 1784335211075, "nav": 99.84}, {"ts": 1784335511075, "nav": 99.84}, {"ts": 1784335811075, "nav": 99.84}, {"ts": 1784336111075, "nav": 99.84}, {"ts": 1784336411075, "nav": 99.84}, {"ts": 1784336711075, "nav": 99.84}, {"ts": 1784337011075, "nav": 99.84}, {"ts": 1784337311075, "nav": 99.84}, {"ts": 1784337611075, "nav": 99.84}, {"ts": 1784337911075, "nav": 99.84}, {"ts": 1784338211075, "nav": 99.84}, {"ts": 1784338511075, "nav": 99.84}, {"ts": 1784338811075, "nav": 99.84}, {"ts": 1784339111075, "nav": 99.84}, {"ts": 1784339411075, "nav": 99.84}, {"ts": 1784339711075, "nav": 99.84}, {"ts": 1784340011075, "nav": 99.84}, {"ts": 1784340311075, "nav": 99.84}, {"ts": 1784340611075, "nav": 99.84}, {"ts": 1784340911075, "nav": 99.84}, {"ts": 1784341211075, "nav": 99.84}, {"ts": 1784341511075, "nav": 99.84}, {"ts": 1784341811075, "nav": 99.84}, {"ts": 1784342111075, "nav": 99.84}, {"ts": 1784342411075, "nav": 99.84}, {"ts": 1784342711075, "nav": 99.84}, {"ts": 1784343011075, "nav": 99.84}, {"ts": 1784343311075, "nav": 99.84}, {"ts": 1784343611075, "nav": 99.84}, {"ts": 1784343911075, "nav": 99.84}, {"ts": 1784344211075, "nav": 99.84}, {"ts": 1784344511075, "nav": 99.84}, {"ts": 1784344811075, "nav": 99.84}, {"ts": 1784345111075, "nav": 99.84}, {"ts": 1784345411075, "nav": 99.84}, {"ts": 1784345711075, "nav": 99.84}, {"ts": 1784346011075, "nav": 99.84}, {"ts": 1784346311075, "nav": 99.84}, {"ts": 1784346611075, "nav": 99.84}, {"ts": 1784346911075, "nav": 99.84}, {"ts": 1784347211075, "nav": 99.84}, {"ts": 1784347511075, "nav": 99.84}, {"ts": 1784347811075, "nav": 99.84}, {"ts": 1784348111075, "nav": 99.84}, {"ts": 1784348411075, "nav": 99.84}, {"ts": 1784348711075, "nav": 99.84}, {"ts": 1784349011075, "nav": 99.84}, {"ts": 1784349311075, "nav": 99.84}, {"ts": 1784349611075, "nav": 99.84}, {"ts": 1784349911075, "nav": 99.84}, {"ts": 1784350211075, "nav": 99.84}, {"ts": 1784350511075, "nav": 99.84}, {"ts": 1784350811075, "nav": 99.84}, {"ts": 1784351111075, "nav": 99.84}, {"ts": 1784351411075, "nav": 99.84}, {"ts": 1784351711075, "nav": 99.84}, {"ts": 1784352011075, "nav": 99.84}, {"ts": 1784352311075, "nav": 99.84}, {"ts": 1784352611075, "nav": 99.84}, {"ts": 1784352911075, "nav": 99.84}, {"ts": 1784353211075, "nav": 99.84}, {"ts": 1784353511075, "nav": 99.84}, {"ts": 1784353811075, "nav": 99.84}, {"ts": 1784354111075, "nav": 99.84}, {"ts": 1784354411075, "nav": 99.84}, {"ts": 1784354711075, "nav": 99.84}, {"ts": 1784355011075, "nav": 99.84}, {"ts": 1784355311075, "nav": 99.84}, {"ts": 1784355611075, "nav": 99.84}, {"ts": 1784355911075, "nav": 99.84}, {"ts": 1784356211075, "nav": 99.84}, {"ts": 1784356511075, "nav": 99.84}, {"ts": 1784356811075, "nav": 99.84}, {"ts": 1784357111075, "nav": 99.84}, {"ts": 1784357411075, "nav": 99.84}, {"ts": 1784357711075, "nav": 99.84}, {"ts": 1784358011075, "nav": 99.84}, {"ts": 1784358311075, "nav": 99.84}, {"ts": 1784358611075, "nav": 99.84}, {"ts": 1784358911075, "nav": 99.84}, {"ts": 1784359211075, "nav": 99.84}, {"ts": 1784359511075, "nav": 99.84}, {"ts": 1784359811075, "nav": 99.84}, {"ts": 1784360111075, "nav": 99.84}, {"ts": 1784360411075, "nav": 99.84}, {"ts": 1784360711075, "nav": 99.84}, {"ts": 1784361011075, "nav": 99.84}, {"ts": 1784361311075, "nav": 99.84}, {"ts": 1784361611075, "nav": 99.84}, {"ts": 1784361911075, "nav": 99.84}, {"ts": 1784362211075, "nav": 99.84}, {"ts": 1784362511075, "nav": 99.84}, {"ts": 1784362811075, "nav": 99.84}, {"ts": 1784363111075, "nav": 99.84}, {"ts": 1784363411075, "nav": 99.84}, {"ts": 1784363711075, "nav": 99.84}, {"ts": 1784364011075, "nav": 99.84}, {"ts": 1784364311075, "nav": 99.84}, {"ts": 1784364611075, "nav": 99.84}, {"ts": 1784364911075, "nav": 99.84}, {"ts": 1784365211075, "nav": 99.84}, {"ts": 1784365511075, "nav": 99.84}, {"ts": 1784365811075, "nav": 99.84}, {"ts": 1784366111075, "nav": 99.84}, {"ts": 1784366411075, "nav": 99.84}, {"ts": 1784366711075, "nav": 99.84}, {"ts": 1784367011075, "nav": 99.84}, {"ts": 1784367311075, "nav": 99.84}, {"ts": 1784367611075, "nav": 99.84}, {"ts": 1784367911075, "nav": 99.84}, {"ts": 1784368211075, "nav": 99.84}, {"ts": 1784368511075, "nav": 99.84}, {"ts": 1784368811075, "nav": 99.84}, {"ts": 1784369111075, "nav": 99.84}, {"ts": 1784369411075, "nav": 99.84}, {"ts": 1784369711075, "nav": 99.84}, {"ts": 1784370011075, "nav": 99.84}, {"ts": 1784370311075, "nav": 99.84}, {"ts": 1784370611075, "nav": 99.84}, {"ts": 1784370911075, "nav": 99.84}, {"ts": 1784371211075, "nav": 99.84}, {"ts": 1784371511075, "nav": 99.84}, {"ts": 1784371811075, "nav": 99.84}, {"ts": 1784372111075, "nav": 99.84}, {"ts": 1784372411075, "nav": 99.84}, {"ts": 1784372711075, "nav": 99.84}, {"ts": 1784373011075, "nav": 99.84}, {"ts": 1784373311075, "nav": 99.84}, {"ts": 1784373611075, "nav": 99.84}, {"ts": 1784373911075, "nav": 99.84}, {"ts": 1784374211075, "nav": 99.84}, {"ts": 1784374511075, "nav": 99.84}, {"ts": 1784374811075, "nav": 99.84}, {"ts": 1784375111075, "nav": 99.84}, {"ts": 1784375411075, "nav": 99.84}, {"ts": 1784375711075, "nav": 99.84}, {"ts": 1784376011075, "nav": 99.84}, {"ts": 1784376311075, "nav": 99.84}, {"ts": 1784376611075, "nav": 99.84}, {"ts": 1784376911075, "nav": 99.84}, {"ts": 1784377211075, "nav": 99.84}, {"ts": 1784377511075, "nav": 99.84}, {"ts": 1784377811075, "nav": 99.84}, {"ts": 1784378111075, "nav": 99.84}, {"ts": 1784378411075, "nav": 99.84}, {"ts": 1784378711075, "nav": 99.84}, {"ts": 1784379011075, "nav": 99.84}, {"ts": 1784379311075, "nav": 99.84}, {"ts": 1784379611075, "nav": 99.84}, {"ts": 1784379911075, "nav": 99.84}, {"ts": 1784380211075, "nav": 99.84}, {"ts": 1784380511075, "nav": 99.84}, {"ts": 1784380811075, "nav": 99.84}, {"ts": 1784381111075, "nav": 99.84}, {"ts": 1784381411075, "nav": 99.84}, {"ts": 1784381711075, "nav": 99.84}, {"ts": 1784382011075, "nav": 99.84}, {"ts": 1784382311075, "nav": 99.84}, {"ts": 1784382611075, "nav": 99.84}, {"ts": 1784382911075, "nav": 99.84}, {"ts": 1784383211075, "nav": 99.84}, {"ts": 1784383511075, "nav": 99.84}, {"ts": 1784383811075, "nav": 99.84}, {"ts": 1784384111075, "nav": 99.84}, {"ts": 1784384411075, "nav": 99.84}, {"ts": 1784384711075, "nav": 99.84}, {"ts": 1784385011075, "nav": 99.84}, {"ts": 1784385311075, "nav": 99.84}, {"ts": 1784385611075, "nav": 99.84}, {"ts": 1784385911075, "nav": 99.84}, {"ts": 1784386211075, "nav": 99.84}, {"ts": 1784386511075, "nav": 99.84}, {"ts": 1784386811075, "nav": 99.84}, {"ts": 1784387111075, "nav": 99.84}, {"ts": 1784387411075, "nav": 99.84}, {"ts": 1784387711075, "nav": 99.84}, {"ts": 1784388011075, "nav": 99.84}, {"ts": 1784388311075, "nav": 99.84}, {"ts": 1784388611075, "nav": 99.84}, {"ts": 1784388911075, "nav": 99.84}, {"ts": 1784389211075, "nav": 99.84}, {"ts": 1784389511075, "nav": 99.84}, {"ts": 1784389811075, "nav": 99.84}, {"ts": 1784390111075, "nav": 99.84}, {"ts": 1784390411075, "nav": 99.84}, {"ts": 1784390711075, "nav": 99.84}, {"ts": 1784391011075, "nav": 99.84}, {"ts": 1784391311075, "nav": 99.84}, {"ts": 1784391611075, "nav": 99.84}, {"ts": 1784391911075, "nav": 99.84}, {"ts": 1784392211075, "nav": 99.84}, {"ts": 1784392511075, "nav": 99.84}, {"ts": 1784392811075, "nav": 99.84}, {"ts": 1784393111075, "nav": 99.83}, {"ts": 1784393411075, "nav": 99.85}, {"ts": 1784393711075, "nav": 99.9}, {"ts": 1784394011075, "nav": 99.91}, {"ts": 1784394311075, "nav": 99.88}, {"ts": 1784394611075, "nav": 99.91}, {"ts": 1784394911075, "nav": 99.91}, {"ts": 1784395211075, "nav": 99.88}, {"ts": 1784395511075, "nav": 99.85}, {"ts": 1784395811075, "nav": 99.81}, {"ts": 1784396111075, "nav": 99.84}, {"ts": 1784396411075, "nav": 99.85}, {"ts": 1784396711075, "nav": 99.88}, {"ts": 1784397011075, "nav": 99.88}, {"ts": 1784397311075, "nav": 99.88}, {"ts": 1784397611075, "nav": 99.88}, {"ts": 1784397911075, "nav": 99.85}, {"ts": 1784398211075, "nav": 99.86}, {"ts": 1784398511075, "nav": 99.85}, {"ts": 1784398811075, "nav": 99.9}, {"ts": 1784399111075, "nav": 99.95}, {"ts": 1784399411075, "nav": 99.9}, {"ts": 1784399711075, "nav": 99.85}, {"ts": 1784400011075, "nav": 99.86}, {"ts": 1784400311075, "nav": 99.85}, {"ts": 1784400611075, "nav": 99.84}, {"ts": 1784400911075, "nav": 99.84}, {"ts": 1784401211075, "nav": 99.84}, {"ts": 1784401511075, "nav": 99.85}, {"ts": 1784401811075, "nav": 99.85}, {"ts": 1784402111075, "nav": 99.86}, {"ts": 1784402411075, "nav": 99.85}, {"ts": 1784402711075, "nav": 99.86}, {"ts": 1784403011075, "nav": 99.83}, {"ts": 1784403311075, "nav": 99.83}, {"ts": 1784403611075, "nav": 99.86}, {"ts": 1784403911075, "nav": 99.86}, {"ts": 1784404211075, "nav": 99.83}, {"ts": 1784404511075, "nav": 99.85}, {"ts": 1784404811075, "nav": 99.83}, {"ts": 1784405111075, "nav": 99.83}, {"ts": 1784405411075, "nav": 99.81}, {"ts": 1784405711075, "nav": 99.82}, {"ts": 1784406011075, "nav": 99.82}, {"ts": 1784406311075, "nav": 99.82}, {"ts": 1784406611075, "nav": 99.81}, {"ts": 1784406911075, "nav": 99.87}, {"ts": 1784407211075, "nav": 99.86}, {"ts": 1784407511075, "nav": 99.88}, {"ts": 1784407811075, "nav": 99.93}, {"ts": 1784408111075, "nav": 99.94}, {"ts": 1784408411075, "nav": 99.9}, {"ts": 1784408711075, "nav": 99.88}, {"ts": 1784409011075, "nav": 99.87}, {"ts": 1784409311075, "nav": 99.9}, {"ts": 1784409611075, "nav": 99.92}, {"ts": 1784409911075, "nav": 99.9}, {"ts": 1784410211075, "nav": 99.9}, {"ts": 1784410511075, "nav": 99.9}, {"ts": 1784410811075, "nav": 99.88}, {"ts": 1784411111075, "nav": 99.92}, {"ts": 1784411411075, "nav": 99.92}, {"ts": 1784411711075, "nav": 99.96}, {"ts": 1784412011075, "nav": 99.99}, {"ts": 1784412311075, "nav": 99.97}, {"ts": 1784412611075, "nav": 99.96}, {"ts": 1784412911075, "nav": 99.97}, {"ts": 1784413211075, "nav": 99.93}, {"ts": 1784413511075, "nav": 99.92}, {"ts": 1784413811075, "nav": 99.92}, {"ts": 1784414111075, "nav": 99.91}, {"ts": 1784414411075, "nav": 99.9}, {"ts": 1784414711075, "nav": 99.9}, {"ts": 1784415011075, "nav": 99.9}, {"ts": 1784415311075, "nav": 99.92}, {"ts": 1784415611075, "nav": 99.89}, {"ts": 1784415911075, "nav": 99.91}, {"ts": 1784416211075, "nav": 99.89}, {"ts": 1784416511075, "nav": 99.94}, {"ts": 1784416811075, "nav": 99.94}, {"ts": 1784417111075, "nav": 99.92}, {"ts": 1784417411075, "nav": 99.92}, {"ts": 1784417711075, "nav": 99.93}, {"ts": 1784418011075, "nav": 99.93}, {"ts": 1784418311075, "nav": 99.92}, {"ts": 1784418611075, "nav": 99.92}, {"ts": 1784418911075, "nav": 99.9}, {"ts": 1784419211075, "nav": 99.89}, {"ts": 1784419511075, "nav": 99.91}, {"ts": 1784419811075, "nav": 99.92}, {"ts": 1784420111075, "nav": 99.91}, {"ts": 1784420411075, "nav": 99.9}, {"ts": 1784420711075, "nav": 99.92}, {"ts": 1784421011075, "nav": 99.91}, {"ts": 1784421311075, "nav": 99.91}, {"ts": 1784421611075, "nav": 99.92}, {"ts": 1784421911075, "nav": 99.93}, {"ts": 1784422211075, "nav": 99.98}, {"ts": 1784422511075, "nav": 100.03}, {"ts": 1784422811075, "nav": 100.03}, {"ts": 1784423111075, "nav": 100.02}, {"ts": 1784423411075, "nav": 99.98}, {"ts": 1784423711075, "nav": 100.02}, {"ts": 1784424011075, "nav": 100.04}, {"ts": 1784424311075, "nav": 100.04}, {"ts": 1784424611075, "nav": 100.05}, {"ts": 1784424911075, "nav": 100.05}, {"ts": 1784425211075, "nav": 100.1}, {"ts": 1784425511075, "nav": 100.07}, {"ts": 1784425811075, "nav": 100.07}, {"ts": 1784426111075, "nav": 100.08}, {"ts": 1784426411075, "nav": 100.11}, {"ts": 1784426711075, "nav": 100.11}, {"ts": 1784427011075, "nav": 100.14}, {"ts": 1784427311075, "nav": 100.16}, {"ts": 1784427611075, "nav": 100.11}, {"ts": 1784427911075, "nav": 100.1}, {"ts": 1784428211075, "nav": 100.03}, {"ts": 1784428511075, "nav": 100.14}, {"ts": 1784428811075, "nav": 100.1}, {"ts": 1784429111075, "nav": 100.07}, {"ts": 1784429411075, "nav": 100.12}, {"ts": 1784429711075, "nav": 100.09}, {"ts": 1784430011075, "nav": 100.08}, {"ts": 1784430311075, "nav": 100.11}, {"ts": 1784430611075, "nav": 100.1}, {"ts": 1784430911075, "nav": 100.09}, {"ts": 1784431211075, "nav": 100.08}, {"ts": 1784431511075, "nav": 100.06}, {"ts": 1784431811075, "nav": 100.09}, {"ts": 1784432111075, "nav": 100.08}, {"ts": 1784432411075, "nav": 100.1}, {"ts": 1784432711075, "nav": 100.12}, {"ts": 1784433011075, "nav": 100.11}, {"ts": 1784433311075, "nav": 100.09}, {"ts": 1784433611075, "nav": 100.12}, {"ts": 1784433911075, "nav": 100.15}, {"ts": 1784434211075, "nav": 100.11}, {"ts": 1784434511075, "nav": 100.09}, {"ts": 1784434811075, "nav": 100.12}, {"ts": 1784435111075, "nav": 100.1}, {"ts": 1784435411075, "nav": 100.15}, {"ts": 1784435711075, "nav": 100.14}, {"ts": 1784436011075, "nav": 100.14}, {"ts": 1784436311075, "nav": 100.12}, {"ts": 1784436611075, "nav": 100.1}, {"ts": 1784436911075, "nav": 100.1}, {"ts": 1784437211075, "nav": 100.12}, {"ts": 1784437511075, "nav": 100.13}, {"ts": 1784437811075, "nav": 100.12}, {"ts": 1784438111075, "nav": 100.13}, {"ts": 1784438411075, "nav": 100.14}, {"ts": 1784438711075, "nav": 100.14}, {"ts": 1784439011075, "nav": 100.12}, {"ts": 1784439311075, "nav": 100.14}, {"ts": 1784439611075, "nav": 100.13}, {"ts": 1784439911075, "nav": 100.14}, {"ts": 1784440211075, "nav": 100.14}, {"ts": 1784440511075, "nav": 100.13}, {"ts": 1784440811075, "nav": 100.13}, {"ts": 1784441111075, "nav": 100.15}, {"ts": 1784441411075, "nav": 100.13}, {"ts": 1784441711075, "nav": 100.14}, {"ts": 1784442011075, "nav": 100.16}, {"ts": 1784442311075, "nav": 100.15}, {"ts": 1784442611075, "nav": 100.13}, {"ts": 1784442911075, "nav": 100.15}, {"ts": 1784443211075, "nav": 100.16}, {"ts": 1784443511075, "nav": 100.14}, {"ts": 1784443811075, "nav": 100.14}, {"ts": 1784444111075, "nav": 100.14}, {"ts": 1784444411075, "nav": 100.14}, {"ts": 1784444711075, "nav": 100.17}, {"ts": 1784445011075, "nav": 100.16}, {"ts": 1784445311075, "nav": 100.14}, {"ts": 1784445611075, "nav": 100.15}, {"ts": 1784445911075, "nav": 100.15}, {"ts": 1784446211075, "nav": 100.16}, {"ts": 1784446511075, "nav": 100.2}, {"ts": 1784446811075, "nav": 100.22}, {"ts": 1784447111075, "nav": 100.19}, {"ts": 1784447411075, "nav": 100.18}, {"ts": 1784447711075, "nav": 100.18}, {"ts": 1784448011075, "nav": 100.2}, {"ts": 1784448311075, "nav": 100.23}, {"ts": 1784448611075, "nav": 100.27}, {"ts": 1784448911075, "nav": 100.26}, {"ts": 1784449211075, "nav": 100.29}, {"ts": 1784449511075, "nav": 100.32}, {"ts": 1784449811075, "nav": 100.28}, {"ts": 1784450111075, "nav": 100.3}, {"ts": 1784450411075, "nav": 100.32}, {"ts": 1784450711075, "nav": 100.3}, {"ts": 1784451011075, "nav": 100.38}, {"ts": 1784451311075, "nav": 100.4}, {"ts": 1784451611075, "nav": 100.4}, {"ts": 1784451911075, "nav": 100.36}, {"ts": 1784452211075, "nav": 100.32}, {"ts": 1784452511075, "nav": 100.32}, {"ts": 1784452811075, "nav": 100.23}, {"ts": 1784453111075, "nav": 100.28}, {"ts": 1784453411075, "nav": 100.25}, {"ts": 1784453711075, "nav": 100.26}, {"ts": 1784454011075, "nav": 100.27}, {"ts": 1784454311075, "nav": 100.3}, {"ts": 1784454611075, "nav": 100.3}, {"ts": 1784454911075, "nav": 100.34}, {"ts": 1784455211075, "nav": 100.32}, {"ts": 1784455511075, "nav": 100.27}, {"ts": 1784455811075, "nav": 100.25}, {"ts": 1784456111075, "nav": 100.26}, {"ts": 1784456411075, "nav": 100.28}, {"ts": 1784456711075, "nav": 100.31}, {"ts": 1784457011075, "nav": 100.29}, {"ts": 1784457311075, "nav": 100.27}, {"ts": 1784457611075, "nav": 100.31}, {"ts": 1784457911075, "nav": 100.32}, {"ts": 1784458211075, "nav": 100.35}, {"ts": 1784458511075, "nav": 100.34}, {"ts": 1784458811075, "nav": 100.32}, {"ts": 1784459111075, "nav": 100.33}, {"ts": 1784459411075, "nav": 100.34}, {"ts": 1784459711075, "nav": 100.31}, {"ts": 1784460011075, "nav": 100.31}, {"ts": 1784460311075, "nav": 100.32}, {"ts": 1784460611075, "nav": 100.29}, {"ts": 1784460911075, "nav": 100.28}, {"ts": 1784461211075, "nav": 100.25}, {"ts": 1784461511075, "nav": 100.24}, {"ts": 1784461811075, "nav": 100.25}, {"ts": 1784462111075, "nav": 100.28}, {"ts": 1784462411075, "nav": 100.24}, {"ts": 1784462711075, "nav": 100.21}, {"ts": 1784463011075, "nav": 100.21}, {"ts": 1784463311075, "nav": 100.2}, {"ts": 1784463611075, "nav": 100.24}, {"ts": 1784463911075, "nav": 100.31}, {"ts": 1784464211075, "nav": 100.31}, {"ts": 1784464511075, "nav": 100.34}, {"ts": 1784464811075, "nav": 100.32}, {"ts": 1784465111075, "nav": 100.35}, {"ts": 1784465411075, "nav": 100.31}, {"ts": 1784465711075, "nav": 100.32}, {"ts": 1784466011075, "nav": 100.31}, {"ts": 1784466311075, "nav": 100.32}, {"ts": 1784466611075, "nav": 100.32}, {"ts": 1784466911075, "nav": 100.36}, {"ts": 1784467211075, "nav": 100.4}, {"ts": 1784467511075, "nav": 100.37}, {"ts": 1784467811075, "nav": 100.41}, {"ts": 1784468111075, "nav": 100.4}, {"ts": 1784468411075, "nav": 100.4}, {"ts": 1784468711075, "nav": 100.41}, {"ts": 1784469011075, "nav": 100.42}, {"ts": 1784469311075, "nav": 100.43}, {"ts": 1784469611075, "nav": 100.39}, {"ts": 1784469911075, "nav": 100.39}, {"ts": 1784470211075, "nav": 100.4}, {"ts": 1784470511075, "nav": 100.35}, {"ts": 1784470811075, "nav": 100.38}, {"ts": 1784471111075, "nav": 100.34}, {"ts": 1784471411075, "nav": 100.32}, {"ts": 1784471711075, "nav": 100.34}, {"ts": 1784472011075, "nav": 100.34}, {"ts": 1784472311075, "nav": 100.35}, {"ts": 1784472611075, "nav": 100.38}, {"ts": 1784472911075, "nav": 100.34}, {"ts": 1784473211075, "nav": 100.34}, {"ts": 1784473511075, "nav": 100.34}, {"ts": 1784473811075, "nav": 100.33}, {"ts": 1784474111075, "nav": 100.37}, {"ts": 1784474411075, "nav": 100.35}, {"ts": 1784474711075, "nav": 100.37}, {"ts": 1784475011075, "nav": 100.33}, {"ts": 1784475311075, "nav": 100.35}, {"ts": 1784475611075, "nav": 100.33}, {"ts": 1784475911075, "nav": 100.35}, {"ts": 1784476211075, "nav": 100.33}, {"ts": 1784476511075, "nav": 100.34}, {"ts": 1784476811075, "nav": 100.33}, {"ts": 1784477111075, "nav": 100.35}, {"ts": 1784477411075, "nav": 100.26}, {"ts": 1784477711075, "nav": 100.22}, {"ts": 1784478011075, "nav": 100.24}, {"ts": 1784478311075, "nav": 100.26}, {"ts": 1784478611075, "nav": 100.26}, {"ts": 1784478911075, "nav": 100.21}, {"ts": 1784479211075, "nav": 100.22}, {"ts": 1784479511075, "nav": 100.19}, {"ts": 1784479811075, "nav": 100.19}, {"ts": 1784480111075, "nav": 100.19}, {"ts": 1784480411075, "nav": 100.19}, {"ts": 1784480711075, "nav": 100.19}, {"ts": 1784481011075, "nav": 100.19}, {"ts": 1784481311075, "nav": 100.19}, {"ts": 1784481611075, "nav": 100.19}, {"ts": 1784481911075, "nav": 100.19}, {"ts": 1784482211075, "nav": 100.19}, {"ts": 1784482511075, "nav": 100.19}, {"ts": 1784482811075, "nav": 100.19}, {"ts": 1784483111075, "nav": 100.16}, {"ts": 1784483411075, "nav": 100.18}, {"ts": 1784483711075, "nav": 100.18}, {"ts": 1784484011075, "nav": 100.15}, {"ts": 1784484311075, "nav": 100.12}, {"ts": 1784484611075, "nav": 100.2}, {"ts": 1784484911075, "nav": 100.2}, {"ts": 1784485211075, "nav": 100.17}, {"ts": 1784485511075, "nav": 100.17}, {"ts": 1784485811075, "nav": 100.17}, {"ts": 1784486111075, "nav": 100.21}, {"ts": 1784486411075, "nav": 100.21}, {"ts": 1784486711075, "nav": 100.09}, {"ts": 1784487011075, "nav": 100.09}, {"ts": 1784487311075, "nav": 100.13}, {"ts": 1784487611075, "nav": 100.14}, {"ts": 1784487911075, "nav": 100.14}, {"ts": 1784488211075, "nav": 100.16}, {"ts": 1784488511075, "nav": 100.16}, {"ts": 1784488811075, "nav": 100.14}, {"ts": 1784489111075, "nav": 100.14}, {"ts": 1784489411075, "nav": 100.14}, {"ts": 1784489711075, "nav": 100.14}, {"ts": 1784490011075, "nav": 100.14}, {"ts": 1784490311075, "nav": 100.09}, {"ts": 1784490611075, "nav": 100.09}, {"ts": 1784490911075, "nav": 100.09}, {"ts": 1784491211075, "nav": 100.09}, {"ts": 1784491511075, "nav": 100.12}, {"ts": 1784491811075, "nav": 100.05}, {"ts": 1784492111075, "nav": 100.1}, {"ts": 1784492411075, "nav": 100.08}, {"ts": 1784492711075, "nav": 100.09}, {"ts": 1784493011075, "nav": 100.09}, {"ts": 1784493311075, "nav": 100.09}, {"ts": 1784493611075, "nav": 100.09}, {"ts": 1784493911075, "nav": 100.08}, {"ts": 1784494211075, "nav": 100.05}, {"ts": 1784494511075, "nav": 100.06}, {"ts": 1784494811075, "nav": 100.07}, {"ts": 1784495111075, "nav": 100.08}, {"ts": 1784495411075, "nav": 100.06}, {"ts": 1784495711075, "nav": 100.06}, {"ts": 1784496011075, "nav": 100.06}, {"ts": 1784496311075, "nav": 100.04}, {"ts": 1784496611075, "nav": 100.04}, {"ts": 1784496911075, "nav": 100.04}, {"ts": 1784497211075, "nav": 100.07}, {"ts": 1784497511075, "nav": 100.09}, {"ts": 1784497811075, "nav": 100.08}, {"ts": 1784498111075, "nav": 100.06}, {"ts": 1784498411075, "nav": 100.08}, {"ts": 1784498711075, "nav": 100.05}, {"ts": 1784499011075, "nav": 100.08}, {"ts": 1784499311075, "nav": 100.37}, {"ts": 1784499611075, "nav": 100.26}, {"ts": 1784499911075, "nav": 100.23}, {"ts": 1784500211075, "nav": 100.25}, {"ts": 1784500511075, "nav": 100.29}, {"ts": 1784500811075, "nav": 100.28}, {"ts": 1784501111075, "nav": 100.28}, {"ts": 1784501411075, "nav": 100.3}, {"ts": 1784501711075, "nav": 100.28}, {"ts": 1784502011075, "nav": 100.27}, {"ts": 1784502311075, "nav": 100.27}, {"ts": 1784502611075, "nav": 100.35}, {"ts": 1784502911075, "nav": 100.36}, {"ts": 1784503211075, "nav": 100.5}, {"ts": 1784503511075, "nav": 100.5}, {"ts": 1784503811075, "nav": 100.49}, {"ts": 1784504111075, "nav": 100.57}, {"ts": 1784504411075, "nav": 100.55}, {"ts": 1784504711075, "nav": 100.53}, {"ts": 1784505011075, "nav": 100.42}, {"ts": 1784505311075, "nav": 100.42}, {"ts": 1784505611075, "nav": 100.42}, {"ts": 1784505911075, "nav": 100.41}, {"ts": 1784506211075, "nav": 100.7}, {"ts": 1784506511075, "nav": 100.78}, {"ts": 1784506811075, "nav": 100.72}, {"ts": 1784507111075, "nav": 100.63}], "1h": [{"ts": 1783643111075, "nav": 101.03}, {"ts": 1783646711075, "nav": 101.03}, {"ts": 1783650311075, "nav": 101.03}, {"ts": 1783653911075, "nav": 101.03}, {"ts": 1783657511075, "nav": 101.03}, {"ts": 1783661111075, "nav": 101.03}, {"ts": 1783664711075, "nav": 100.67}, {"ts": 1783668311075, "nav": 100.69}, {"ts": 1783671911075, "nav": 100.33}, {"ts": 1783675511075, "nav": 100.99}, {"ts": 1783679111075, "nav": 101.63}, {"ts": 1783682711075, "nav": 102.15}, {"ts": 1783686311075, "nav": 102.07}, {"ts": 1783689911075, "nav": 102.18}, {"ts": 1783693511075, "nav": 102.37}, {"ts": 1783697111075, "nav": 102.78}, {"ts": 1783700711075, "nav": 102.06}, {"ts": 1783704311075, "nav": 102.16}, {"ts": 1783707911075, "nav": 102.19}, {"ts": 1783711511075, "nav": 102.05}, {"ts": 1783715111075, "nav": 101.63}, {"ts": 1783718711075, "nav": 101.63}, {"ts": 1783722311075, "nav": 101.63}, {"ts": 1783725911075, "nav": 101.63}, {"ts": 1783729511075, "nav": 101.63}, {"ts": 1783733111075, "nav": 101.63}, {"ts": 1783736711075, "nav": 101.63}, {"ts": 1783740311075, "nav": 101.63}, {"ts": 1783743911075, "nav": 101.63}, {"ts": 1783747511075, "nav": 101.63}, {"ts": 1783751111075, "nav": 101.63}, {"ts": 1783754711075, "nav": 101.63}, {"ts": 1783758311075, "nav": 101.63}, {"ts": 1783761911075, "nav": 101.63}, {"ts": 1783765511075, "nav": 101.63}, {"ts": 1783769111075, "nav": 101.63}, {"ts": 1783772711075, "nav": 101.63}, {"ts": 1783776311075, "nav": 101.63}, {"ts": 1783779911075, "nav": 101.61}, {"ts": 1783783511075, "nav": 101.6}, {"ts": 1783787111075, "nav": 101.55}, {"ts": 1783790711075, "nav": 101.6}, {"ts": 1783794311075, "nav": 101.63}, {"ts": 1783797911075, "nav": 101.66}, {"ts": 1783801511075, "nav": 101.62}, {"ts": 1783805111075, "nav": 101.6}, {"ts": 1783808711075, "nav": 101.57}, {"ts": 1783812311075, "nav": 101.24}, {"ts": 1783815911075, "nav": 101.05}, {"ts": 1783819511075, "nav": 101.12}, {"ts": 1783823111075, "nav": 101.01}, {"ts": 1783826711075, "nav": 101.16}, {"ts": 1783830311075, "nav": 101.3}, {"ts": 1783833911075, "nav": 101.37}, {"ts": 1783837511075, "nav": 101.22}, {"ts": 1783841111075, "nav": 101.18}, {"ts": 1783844711075, "nav": 101.27}, {"ts": 1783848311075, "nav": 101.04}, {"ts": 1783851911075, "nav": 101.02}, {"ts": 1783855511075, "nav": 101.08}, {"ts": 1783859111075, "nav": 101.08}, {"ts": 1783862711075, "nav": 101.42}, {"ts": 1783866311075, "nav": 101.23}, {"ts": 1783869911075, "nav": 101.23}, {"ts": 1783873511075, "nav": 101.23}, {"ts": 1783877111075, "nav": 101.23}, {"ts": 1783880711075, "nav": 101.19}, {"ts": 1783884311075, "nav": 101.23}, {"ts": 1783887911075, "nav": 101.23}, {"ts": 1783891511075, "nav": 101.2}, {"ts": 1783895111075, "nav": 101.02}, {"ts": 1783898711075, "nav": 100.64}, {"ts": 1783902311075, "nav": 101.16}, {"ts": 1783905911075, "nav": 99.83}, {"ts": 1783909511075, "nav": 99.78}, {"ts": 1783913111075, "nav": 99.59}, {"ts": 1783916711075, "nav": 99.6}, {"ts": 1783920311075, "nav": 99.54}, {"ts": 1783923911075, "nav": 99.47}, {"ts": 1783927511075, "nav": 99.47}, {"ts": 1783931111075, "nav": 99.5}, {"ts": 1783934711075, "nav": 99.67}, {"ts": 1783938311075, "nav": 99.62}, {"ts": 1783941911075, "nav": 99.76}, {"ts": 1783945511075, "nav": 99.67}, {"ts": 1783949111075, "nav": 99.75}, {"ts": 1783952711075, "nav": 99.39}, {"ts": 1783956311075, "nav": 99.48}, {"ts": 1783959911075, "nav": 98.86}, {"ts": 1783963511075, "nav": 98.58}, {"ts": 1783967111075, "nav": 98.54}, {"ts": 1783970711075, "nav": 98.42}, {"ts": 1783974311075, "nav": 98.42}, {"ts": 1783977911075, "nav": 98.42}, {"ts": 1783981511075, "nav": 98.42}, {"ts": 1783985111075, "nav": 98.42}, {"ts": 1783988711075, "nav": 99.18}, {"ts": 1783992311075, "nav": 99.25}, {"ts": 1783995911075, "nav": 99.17}, {"ts": 1783999511075, "nav": 99.1}, {"ts": 1784003111075, "nav": 99.16}, {"ts": 1784006711075, "nav": 99.31}, {"ts": 1784010311075, "nav": 99.39}, {"ts": 1784013911075, "nav": 99.35}, {"ts": 1784017511075, "nav": 99.35}, {"ts": 1784021111075, "nav": 99.33}, {"ts": 1784024711075, "nav": 99.33}, {"ts": 1784028311075, "nav": 99.41}, {"ts": 1784031911075, "nav": 99.36}, {"ts": 1784035511075, "nav": 99.55}, {"ts": 1784039111075, "nav": 99.1}, {"ts": 1784042711075, "nav": 99.26}, {"ts": 1784046311075, "nav": 99.23}, {"ts": 1784049911075, "nav": 99.29}, {"ts": 1784053511075, "nav": 99.32}, {"ts": 1784057111075, "nav": 99.28}, {"ts": 1784060711075, "nav": 99.3}, {"ts": 1784064311075, "nav": 99.38}, {"ts": 1784067911075, "nav": 99.36}, {"ts": 1784071511075, "nav": 99.51}, {"ts": 1784075111075, "nav": 99.48}, {"ts": 1784078711075, "nav": 99.53}, {"ts": 1784082311075, "nav": 99.53}, {"ts": 1784085911075, "nav": 99.61}, {"ts": 1784089511075, "nav": 99.7}, {"ts": 1784093111075, "nav": 99.66}, {"ts": 1784096711075, "nav": 99.69}, {"ts": 1784100311075, "nav": 99.58}, {"ts": 1784103911075, "nav": 99.5}, {"ts": 1784107511075, "nav": 99.66}, {"ts": 1784111111075, "nav": 99.31}, {"ts": 1784114711075, "nav": 99.22}, {"ts": 1784118311075, "nav": 99.09}, {"ts": 1784121911075, "nav": 99.44}, {"ts": 1784125511075, "nav": 99.25}, {"ts": 1784129111075, "nav": 99.12}, {"ts": 1784132711075, "nav": 98.94}, {"ts": 1784136311075, "nav": 99.8}, {"ts": 1784139911075, "nav": 100.39}, {"ts": 1784143511075, "nav": 100.2}, {"ts": 1784147111075, "nav": 100.39}, {"ts": 1784150711075, "nav": 100.38}, {"ts": 1784154311075, "nav": 100.39}, {"ts": 1784157911075, "nav": 100.35}, {"ts": 1784161511075, "nav": 100.37}, {"ts": 1784165111075, "nav": 100.28}, {"ts": 1784168711075, "nav": 100.32}, {"ts": 1784172311075, "nav": 100.37}, {"ts": 1784175911075, "nav": 100.37}, {"ts": 1784179511075, "nav": 100.41}, {"ts": 1784183111075, "nav": 100.36}, {"ts": 1784186711075, "nav": 100.35}, {"ts": 1784190311075, "nav": 99.82}, {"ts": 1784193911075, "nav": 99.98}, {"ts": 1784197511075, "nav": 99.89}, {"ts": 1784201111075, "nav": 99.8}, {"ts": 1784204711075, "nav": 99.46}, {"ts": 1784208311075, "nav": 99.96}, {"ts": 1784211911075, "nav": 100.55}, {"ts": 1784215511075, "nav": 100.69}, {"ts": 1784219111075, "nav": 100.31}, {"ts": 1784222711075, "nav": 100.21}, {"ts": 1784226311075, "nav": 100.42}, {"ts": 1784229911075, "nav": 100.45}, {"ts": 1784233511075, "nav": 100.43}, {"ts": 1784237111075, "nav": 100.43}, {"ts": 1784240711075, "nav": 100.45}, {"ts": 1784244311075, "nav": 100.27}, {"ts": 1784247911075, "nav": 100.18}, {"ts": 1784251511075, "nav": 100.25}, {"ts": 1784255111075, "nav": 100.17}, {"ts": 1784258711075, "nav": 100.28}, {"ts": 1784262311075, "nav": 100.09}, {"ts": 1784265911075, "nav": 100.03}, {"ts": 1784269511075, "nav": 100.1}, {"ts": 1784273111075, "nav": 99.97}, {"ts": 1784276711075, "nav": 99.84}, {"ts": 1784280311075, "nav": 99.84}, {"ts": 1784283911075, "nav": 99.84}, {"ts": 1784287511075, "nav": 99.84}, {"ts": 1784291111075, "nav": 99.84}, {"ts": 1784294711075, "nav": 99.84}, {"ts": 1784298311075, "nav": 99.84}, {"ts": 1784301911075, "nav": 99.84}, {"ts": 1784305511075, "nav": 99.84}, {"ts": 1784309111075, "nav": 99.84}, {"ts": 1784312711075, "nav": 99.84}, {"ts": 1784316311075, "nav": 99.84}, {"ts": 1784319911075, "nav": 99.84}, {"ts": 1784323511075, "nav": 99.84}, {"ts": 1784327111075, "nav": 99.84}, {"ts": 1784330711075, "nav": 99.84}, {"ts": 1784334311075, "nav": 99.84}, {"ts": 1784337911075, "nav": 99.84}, {"ts": 1784341511075, "nav": 99.84}, {"ts": 1784345111075, "nav": 99.84}, {"ts": 1784348711075, "nav": 99.84}, {"ts": 1784352311075, "nav": 99.84}, {"ts": 1784355911075, "nav": 99.84}, {"ts": 1784359511075, "nav": 99.84}, {"ts": 1784363111075, "nav": 99.84}, {"ts": 1784366711075, "nav": 99.84}, {"ts": 1784370311075, "nav": 99.84}, {"ts": 1784373911075, "nav": 99.84}, {"ts": 1784377511075, "nav": 99.84}, {"ts": 1784381111075, "nav": 99.84}, {"ts": 1784384711075, "nav": 99.84}, {"ts": 1784388311075, "nav": 99.84}, {"ts": 1784391911075, "nav": 99.84}, {"ts": 1784395511075, "nav": 99.85}, {"ts": 1784399111075, "nav": 99.95}, {"ts": 1784402711075, "nav": 99.86}, {"ts": 1784406311075, "nav": 99.82}, {"ts": 1784409911075, "nav": 99.9}, {"ts": 1784413511075, "nav": 99.92}, {"ts": 1784417111075, "nav": 99.92}, {"ts": 1784420711075, "nav": 99.92}, {"ts": 1784424311075, "nav": 100.04}, {"ts": 1784427911075, "nav": 100.1}, {"ts": 1784431511075, "nav": 100.06}, {"ts": 1784435111075, "nav": 100.1}, {"ts": 1784438711075, "nav": 100.14}, {"ts": 1784442311075, "nav": 100.15}, {"ts": 1784445911075, "nav": 100.15}, {"ts": 1784449511075, "nav": 100.32}, {"ts": 1784453111075, "nav": 100.28}, {"ts": 1784456711075, "nav": 100.31}, {"ts": 1784460311075, "nav": 100.32}, {"ts": 1784463911075, "nav": 100.31}, {"ts": 1784467511075, "nav": 100.37}, {"ts": 1784471111075, "nav": 100.34}, {"ts": 1784474711075, "nav": 100.37}, {"ts": 1784478311075, "nav": 100.26}, {"ts": 1784481911075, "nav": 100.19}, {"ts": 1784485511075, "nav": 100.17}, {"ts": 1784489111075, "nav": 100.14}, {"ts": 1784492711075, "nav": 100.09}, {"ts": 1784496311075, "nav": 100.04}, {"ts": 1784499911075, "nav": 100.23}, {"ts": 1784503511075, "nav": 100.5}, {"ts": 1784507111075, "nav": 100.63}], "4h": [{"ts": 1782934428095, "nav": 100.0}, {"ts": 1782948828095, "nav": 100.0}, {"ts": 1782963228095, "nav": 100.0}, {"ts": 1782977628095, "nav": 99.98}, {"ts": 1782992028095, "nav": 100.81}, {"ts": 1783006428095, "nav": 101.04}, {"ts": 1783020828095, "nav": 101.67}, {"ts": 1783035228095, "nav": 101.96}, {"ts": 1783049628095, "nav": 102.39}, {"ts": 1783064028095, "nav": 102.56}, {"ts": 1783078428095, "nav": 102.88}, {"ts": 1783092828095, "nav": 102.74}, {"ts": 1783107228095, "nav": 102.72}, {"ts": 1783121628095, "nav": 102.72}, {"ts": 1783136028095, "nav": 102.72}, {"ts": 1783150428095, "nav": 102.72}, {"ts": 1783164828095, "nav": 102.72}, {"ts": 1783179228095, "nav": 103.14}, {"ts": 1783193628095, "nav": 103.21}, {"ts": 1783208028095, "nav": 103.38}, {"ts": 1783222428095, "nav": 103.44}, {"ts": 1783236828095, "nav": 103.44}, {"ts": 1783251228095, "nav": 103.22}, {"ts": 1783265628095, "nav": 103.44}, {"ts": 1783280028095, "nav": 103.79}, {"ts": 1783294428095, "nav": 103.79}, {"ts": 1783308828095, "nav": 103.38}, {"ts": 1783323228095, "nav": 103.55}, {"ts": 1783337628095, "nav": 103.53}, {"ts": 1783352028095, "nav": 103.06}, {"ts": 1783366428095, "nav": 102.28}, {"ts": 1783380828095, "nav": 101.91}, {"ts": 1783395228095, "nav": 101.05}, {"ts": 1783409628095, "nav": 100.76}, {"ts": 1783424028095, "nav": 100.42}, {"ts": 1783438428095, "nav": 99.9}, {"ts": 1783452828095, "nav": 99.94}, {"ts": 1783467228095, "nav": 100.36}, {"ts": 1783481628095, "nav": 100.72}, {"ts": 1783496028095, "nav": 100.33}, {"ts": 1783510428095, "nav": 99.65}, {"ts": 1783524828095, "nav": 99.97}, {"ts": 1783539228095, "nav": 100.42}, {"ts": 1783553628095, "nav": 100.39}, {"ts": 1783568028095, "nav": 100.51}, {"ts": 1783582428095, "nav": 100.66}, {"ts": 1783596828095, "nav": 100.69}, {"ts": 1783611228095, "nav": 101.03}, {"ts": 1783625628095, "nav": 101.03}, {"ts": 1783640028095, "nav": 101.03}, {"ts": 1783654428095, "nav": 101.03}, {"ts": 1783668828095, "nav": 100.7}, {"ts": 1783683228095, "nav": 102.13}, {"ts": 1783697628095, "nav": 102.58}, {"ts": 1783712028095, "nav": 102.0}, {"ts": 1783726428095, "nav": 101.63}, {"ts": 1783740828095, "nav": 101.63}, {"ts": 1783755228095, "nav": 101.63}, {"ts": 1783769628095, "nav": 101.63}, {"ts": 1783784028095, "nav": 101.59}, {"ts": 1783798428095, "nav": 101.67}, {"ts": 1783812828095, "nav": 101.14}, {"ts": 1783827228095, "nav": 101.16}, {"ts": 1783841628095, "nav": 101.23}, {"ts": 1783856028095, "nav": 101.08}, {"ts": 1783870428095, "nav": 101.23}, {"ts": 1783884828095, "nav": 101.24}, {"ts": 1783899228095, "nav": 100.72}, {"ts": 1783913628095, "nav": 99.58}, {"ts": 1783928028095, "nav": 99.47}, {"ts": 1783942428095, "nav": 99.75}, {"ts": 1783956828095, "nav": 99.46}, {"ts": 1783971228095, "nav": 98.42}, {"ts": 1783985628095, "nav": 98.42}, {"ts": 1784000028095, "nav": 99.1}, {"ts": 1784014428095, "nav": 99.36}, {"ts": 1784028828095, "nav": 99.44}, {"ts": 1784043228095, "nav": 99.34}, {"ts": 1784057628095, "nav": 99.24}, {"ts": 1784072028095, "nav": 99.54}, {"ts": 1784086428095, "nav": 99.66}, {"ts": 1784100828095, "nav": 99.62}, {"ts": 1784115228095, "nav": 99.17}, {"ts": 1784129628095, "nav": 99.28}, {"ts": 1784144028095, "nav": 100.26}, {"ts": 1784158428095, "nav": 100.39}, {"ts": 1784172828095, "nav": 100.4}, {"ts": 1784187228095, "nav": 100.31}, {"ts": 1784201628095, "nav": 99.69}, {"ts": 1784216028095, "nav": 100.71}, {"ts": 1784230428095, "nav": 100.42}, {"ts": 1784244828095, "nav": 100.26}, {"ts": 1784259228095, "nav": 100.25}, {"ts": 1784273628095, "nav": 99.99}, {"ts": 1784288028095, "nav": 99.84}, {"ts": 1784302428095, "nav": 99.84}, {"ts": 1784316828095, "nav": 99.84}, {"ts": 1784331228095, "nav": 99.84}, {"ts": 1784345628095, "nav": 99.84}, {"ts": 1784360028095, "nav": 99.84}, {"ts": 1784374428095, "nav": 99.84}, {"ts": 1784388828095, "nav": 99.84}, {"ts": 1784403228095, "nav": 99.83}, {"ts": 1784417628095, "nav": 99.91}, {"ts": 1784432028095, "nav": 100.08}, {"ts": 1784446428095, "nav": 100.18}, {"ts": 1784460828095, "nav": 100.28}, {"ts": 1784475228095, "nav": 100.35}, {"ts": 1784489628095, "nav": 100.14}, {"ts": 1784504028095, "nav": 100.57}], "1d": [{"ts": 1782934428095, "nav": 100.0}, {"ts": 1783020828095, "nav": 101.67}, {"ts": 1783107228095, "nav": 102.72}, {"ts": 1783193628095, "nav": 103.21}, {"ts": 1783280028095, "nav": 103.79}, {"ts": 1783366428095, "nav": 102.28}, {"ts": 1783452828095, "nav": 99.94}, {"ts": 1783539228095, "nav": 100.42}, {"ts": 1783625628095, "nav": 101.03}, {"ts": 1783712028095, "nav": 102.0}, {"ts": 1783798428095, "nav": 101.67}, {"ts": 1783884828095, "nav": 101.24}, {"ts": 1783971228095, "nav": 98.42}, {"ts": 1784057628095, "nav": 99.24}, {"ts": 1784144028095, "nav": 100.26}, {"ts": 1784230428095, "nav": 100.42}, {"ts": 1784316828095, "nav": 99.84}, {"ts": 1784403228095, "nav": 99.83}, {"ts": 1784489628095, "nav": 100.14}]}, "challenger": {"name": "e70_r50_tp30_mkt", "config": {"name": "e70_r50_tp30_mkt", "min_edge": 70, "rsi_1h_max": 50.0, "tp": 0.03, "sl": 0.012, "market_hours": true}, "equity": 104.37, "return_pct": 4.37, "closed": 22, "wins": 11, "losses": 11, "open": 0, "win_rate": 50.0, "leads": true, "vs_champion_pct": 3.74}}